Workbook

Sheet Summary
A1: OWASP ASVS 5.0 – Compliance Tracker
A5: Chapter | B5: Total Reqs | C5: L1 Total | D5: L1 Compliant | E5: L1 % | F5: L2 Total | G5: L2 Compliant | H5: L2 % | I5: L3 Total | J5: L3 Compliant | K5: L3 % | L5: Overall Compliant | M5: Overall %
A6: V1 – Encoding and Sanitization | B6: 30 | C6: 8 | D6: =COUNTIFS('V1 - Encoding and Sanitization'!$F$2:$F$36,"Compliant",'V1 - Encoding and Sanitization'!$E$2:$E$36,1) -> 4 | E6: =IF(C6=0,"",D6/C6) -> 0.5 | F6: 19 | G6: =COUNTIFS('V1 - Encoding and Sanitization'!$F$2:$F$36,"Compliant",'V1 - Encoding and Sanitization'!$E$2:$E$36,2) -> 11 | H6: =IF(F6=0,"",G6/F6) -> 0.57894737 | I6: 3 | J6: =COUNTIFS('V1 - Encoding and Sanitization'!$F$2:$F$36,"Compliant",'V1 - Encoding and Sanitization'!$E$2:$E$36,3) -> 2 | K6: =IF(I6=0,"",J6/I6) -> 0.66666667 | L6: =COUNTIF('V1 - Encoding and Sanitization'!$F$2:$F$36,"Compliant") -> 17 | M6: =IF(B6=0,"",L6/B6) -> 0.56666667
A7: V2 – Validation and Business Logic | B7: 13 | C7: 4 | D7: =COUNTIFS('V2 - Validation and Business Lo'!$F$2:$F$18,"Compliant",'V2 - Validation and Business Lo'!$E$2:$E$18,1) -> 4 | E7: =IF(C7=0,"",D7/C7) -> 1 | F7: 7 | G7: =COUNTIFS('V2 - Validation and Business Lo'!$F$2:$F$18,"Compliant",'V2 - Validation and Business Lo'!$E$2:$E$18,2) -> 6 | H7: =IF(F7=0,"",G7/F7) -> 0.85714286 | I7: 2 | J7: =COUNTIFS('V2 - Validation and Business Lo'!$F$2:$F$18,"Compliant",'V2 - Validation and Business Lo'!$E$2:$E$18,3) -> 1 | K7: =IF(I7=0,"",J7/I7) -> 0.5 | L7: =COUNTIF('V2 - Validation and Business Lo'!$F$2:$F$18,"Compliant") -> 11 | M7: =IF(B7=0,"",L7/B7) -> 0.84615385
A8: V3 – Web Frontend Security | B8: 31 | C8: 8 | D8: =COUNTIFS('V3 - Web Frontend Security'!$F$2:$F$39,"Compliant",'V3 - Web Frontend Security'!$E$2:$E$39,1) -> 0 | E8: =IF(C8=0,"",D8/C8) -> 0 | F8: 11 | G8: =COUNTIFS('V3 - Web Frontend Security'!$F$2:$F$39,"Compliant",'V3 - Web Frontend Security'!$E$2:$E$39,2) -> 0 | H8: =IF(F8=0,"",G8/F8) -> 0 | I8: 12 | J8: =COUNTIFS('V3 - Web Frontend Security'!$F$2:$F$39,"Compliant",'V3 - Web Frontend Security'!$E$2:$E$39,3) -> 0 | K8: =IF(I8=0,"",J8/I8) -> 0 | L8: =COUNTIF('V3 - Web Frontend Security'!$F$2:$F$39,"Compliant") -> 0 | M8: =IF(B8=0,"",L8/B8) -> 0
A9: V4 – API and Web Service | B9: 16 | C9: 2 | D9: =COUNTIFS('V4 - API and Web Service'!$F$2:$F$21,"Compliant",'V4 - API and Web Service'!$E$2:$E$21,1) -> 1 | E9: =IF(C9=0,"",D9/C9) -> 0.5 | F9: 8 | G9: =COUNTIFS('V4 - API and Web Service'!$F$2:$F$21,"Compliant",'V4 - API and Web Service'!$E$2:$E$21,2) -> 2 | H9: =IF(F9=0,"",G9/F9) -> 0.25 | I9: 6 | J9: =COUNTIFS('V4 - API and Web Service'!$F$2:$F$21,"Compliant",'V4 - API and Web Service'!$E$2:$E$21,3) -> 6 | K9: =IF(I9=0,"",J9/I9) -> 1 | L9: =COUNTIF('V4 - API and Web Service'!$F$2:$F$21,"Compliant") -> 9 | M9: =IF(B9=0,"",L9/B9) -> 0.5625
A10: V5 – File Handling | B10: 13 | C10: 4 | D10: =COUNTIFS('V5 - File Handling'!$F$2:$F$18,"Compliant",'V5 - File Handling'!$E$2:$E$18,1) -> 4 | E10: =IF(C10=0,"",D10/C10) -> 1 | F10: 5 | G10: =COUNTIFS('V5 - File Handling'!$F$2:$F$18,"Compliant",'V5 - File Handling'!$E$2:$E$18,2) -> 5 | H10: =IF(F10=0,"",G10/F10) -> 1 | I10: 4 | J10: =COUNTIFS('V5 - File Handling'!$F$2:$F$18,"Compliant",'V5 - File Handling'!$E$2:$E$18,3) -> 3 | K10: =IF(I10=0,"",J10/I10) -> 0.75 | L10: =COUNTIF('V5 - File Handling'!$F$2:$F$18,"Compliant") -> 12 | M10: =IF(B10=0,"",L10/B10) -> 0.92307692
A11: V6 – Authentication | B11: 47 | C11: 13 | D11: =COUNTIFS('V6 - Authentication'!$F$2:$F$56,"Compliant",'V6 - Authentication'!$E$2:$E$56,1) -> 12 | E11: =IF(C11=0,"",D11/C11) -> 0.92307692 | F11: 22 | G11: =COUNTIFS('V6 - Authentication'!$F$2:$F$56,"Compliant",'V6 - Authentication'!$E$2:$E$56,2) -> 11 | H11: =IF(F11=0,"",G11/F11) -> 0.5 | I11: 12 | J11: =COUNTIFS('V6 - Authentication'!$F$2:$F$56,"Compliant",'V6 - Authentication'!$E$2:$E$56,3) -> 7 | K11: =IF(I11=0,"",J11/I11) -> 0.58333333 | L11: =COUNTIF('V6 - Authentication'!$F$2:$F$56,"Compliant") -> 30 | M11: =IF(B11=0,"",L11/B11) -> 0.63829787
A12: V7 – Session Management | B12: 19 | C12: 6 | D12: =COUNTIFS('V7 - Session Management'!$F$2:$F$26,"Compliant",'V7 - Session Management'!$E$2:$E$26,1) -> 6 | E12: =IF(C12=0,"",D12/C12) -> 1 | F12: 12 | G12: =COUNTIFS('V7 - Session Management'!$F$2:$F$26,"Compliant",'V7 - Session Management'!$E$2:$E$26,2) -> 6 | H12: =IF(F12=0,"",G12/F12) -> 0.5 | I12: 1 | J12: =COUNTIFS('V7 - Session Management'!$F$2:$F$26,"Compliant",'V7 - Session Management'!$E$2:$E$26,3) -> 0 | K12: =IF(I12=0,"",J12/I12) -> 0 | L12: =COUNTIF('V7 - Session Management'!$F$2:$F$26,"Compliant") -> 12 | M12: =IF(B12=0,"",L12/B12) -> 0.63157895
A13: V8 – Authorization | B13: 13 | C13: 4 | D13: =COUNTIFS('V8 - Authorization'!$F$2:$F$18,"Compliant",'V8 - Authorization'!$E$2:$E$18,1) -> 3 | E13: =IF(C13=0,"",D13/C13) -> 0.75 | F13: 3 | G13: =COUNTIFS('V8 - Authorization'!$F$2:$F$18,"Compliant",'V8 - Authorization'!$E$2:$E$18,2) -> 2 | H13: =IF(F13=0,"",G13/F13) -> 0.66666667 | I13: 6 | J13: =COUNTIFS('V8 - Authorization'!$F$2:$F$18,"Compliant",'V8 - Authorization'!$E$2:$E$18,3) -> 3 | K13: =IF(I13=0,"",J13/I13) -> 0.5 | L13: =COUNTIF('V8 - Authorization'!$F$2:$F$18,"Compliant") -> 8 | M13: =IF(B13=0,"",L13/B13) -> 0.61538462
A14: V9 – Self-contained Tokens | B14: 7 | C14: 4 | D14: =COUNTIFS('V9 - Self-contained Tokens'!$F$2:$F$10,"Compliant",'V9 - Self-contained Tokens'!$E$2:$E$10,1) -> 4 | E14: =IF(C14=0,"",D14/C14) -> 1 | F14: 3 | G14: =COUNTIFS('V9 - Self-contained Tokens'!$F$2:$F$10,"Compliant",'V9 - Self-contained Tokens'!$E$2:$E$10,2) -> 2 | H14: =IF(F14=0,"",G14/F14) -> 0.66666667 | I14: 0 | J14: =COUNTIFS('V9 - Self-contained Tokens'!$F$2:$F$10,"Compliant",'V9 - Self-contained Tokens'!$E$2:$E$10,3) -> 0 | K14: =IF(I14=0,"",J14/I14) | L14: =COUNTIF('V9 - Self-contained Tokens'!$F$2:$F$10,"Compliant") -> 6 | M14: =IF(B14=0,"",L14/B14) -> 0.85714286
A15: V10 – OAuth and OIDC | B15: 36 | C15: 5 | D15: =COUNTIFS('V10 - OAuth and OIDC'!$F$2:$F$44,"Compliant",'V10 - OAuth and OIDC'!$E$2:$E$44,1) -> 2 | E15: =IF(C15=0,"",D15/C15) -> 0.4 | F15: 24 | G15: =COUNTIFS('V10 - OAuth and OIDC'!$F$2:$F$44,"Compliant",'V10 - OAuth and OIDC'!$E$2:$E$44,2) -> 3 | H15: =IF(F15=0,"",G15/F15) -> 0.125 | I15: 7 | J15: =COUNTIFS('V10 - OAuth and OIDC'!$F$2:$F$44,"Compliant",'V10 - OAuth and OIDC'!$E$2:$E$44,3) -> 0 | K15: =IF(I15=0,"",J15/I15) -> 0 | L15: =COUNTIF('V10 - OAuth and OIDC'!$F$2:$F$44,"Compliant") -> 5 | M15: =IF(B15=0,"",L15/B15) -> 0.13888889
A16: V11 – Cryptography | B16: 24 | C16: 3 | D16: =COUNTIFS('V11 - Cryptography'!$F$2:$F$32,"Compliant",'V11 - Cryptography'!$E$2:$E$32,1) -> 3 | E16: =IF(C16=0,"",D16/C16) -> 1 | F16: 11 | G16: =COUNTIFS('V11 - Cryptography'!$F$2:$F$32,"Compliant",'V11 - Cryptography'!$E$2:$E$32,2) -> 11 | H16: =IF(F16=0,"",G16/F16) -> 1 | I16: 10 | J16: =COUNTIFS('V11 - Cryptography'!$F$2:$F$32,"Compliant",'V11 - Cryptography'!$E$2:$E$32,3) -> 8 | K16: =IF(I16=0,"",J16/I16) -> 0.8 | L16: =COUNTIF('V11 - Cryptography'!$F$2:$F$32,"Compliant") -> 22 | M16: =IF(B16=0,"",L16/B16) -> 0.91666667
A17: V12 – Secure Communication | B17: 12 | C17: 3 | D17: =COUNTIFS('V12 - Secure Communication'!$F$2:$F$16,"Compliant",'V12 - Secure Communication'!$E$2:$E$16,1) -> 3 | E17: =IF(C17=0,"",D17/C17) -> 1 | F17: 6 | G17: =COUNTIFS('V12 - Secure Communication'!$F$2:$F$16,"Compliant",'V12 - Secure Communication'!$E$2:$E$16,2) -> 5 | H17: =IF(F17=0,"",G17/F17) -> 0.83333333 | I17: 3 | J17: =COUNTIFS('V12 - Secure Communication'!$F$2:$F$16,"Compliant",'V12 - Secure Communication'!$E$2:$E$16,3) -> 2 | K17: =IF(I17=0,"",J17/I17) -> 0.66666667 | L17: =COUNTIF('V12 - Secure Communication'!$F$2:$F$16,"Compliant") -> 10 | M17: =IF(B17=0,"",L17/B17) -> 0.83333333
A18: V13 – Configuration | B18: 21 | C18: 1 | D18: =COUNTIFS('V13 - Configuration'!$F$2:$F$26,"Compliant",'V13 - Configuration'!$E$2:$E$26,1) -> 1 | E18: =IF(C18=0,"",D18/C18) -> 1 | F18: 12 | G18: =COUNTIFS('V13 - Configuration'!$F$2:$F$26,"Compliant",'V13 - Configuration'!$E$2:$E$26,2) -> 12 | H18: =IF(F18=0,"",G18/F18) -> 1 | I18: 8 | J18: =COUNTIFS('V13 - Configuration'!$F$2:$F$26,"Compliant",'V13 - Configuration'!$E$2:$E$26,3) -> 8 | K18: =IF(I18=0,"",J18/I18) -> 1 | L18: =COUNTIF('V13 - Configuration'!$F$2:$F$26,"Compliant") -> 21 | M18: =IF(B18=0,"",L18/B18) -> 1
A19: V14 – Data Protection | B19: 13 | C19: 2 | D19: =COUNTIFS('V14 - Data Protection'!$F$2:$F$17,"Compliant",'V14 - Data Protection'!$E$2:$E$17,1) -> 1 | E19: =IF(C19=0,"",D19/C19) -> 0.5 | F19: 7 | G19: =COUNTIFS('V14 - Data Protection'!$F$2:$F$17,"Compliant",'V14 - Data Protection'!$E$2:$E$17,2) -> 5 | H19: =IF(F19=0,"",G19/F19) -> 0.71428571 | I19: 4 | J19: =COUNTIFS('V14 - Data Protection'!$F$2:$F$17,"Compliant",'V14 - Data Protection'!$E$2:$E$17,3) -> 2 | K19: =IF(I19=0,"",J19/I19) -> 0.5 | L19: =COUNTIF('V14 - Data Protection'!$F$2:$F$17,"Compliant") -> 8 | M19: =IF(B19=0,"",L19/B19) -> 0.61538462
A20: V15 – Secure Coding and Architecture | B20: 21 | C20: 3 | D20: =COUNTIFS('V15 - Secure Coding and Archite'!$F$2:$F$26,"Compliant",'V15 - Secure Coding and Archite'!$E$2:$E$26,1) -> 3 | E20: =IF(C20=0,"",D20/C20) -> 1 | F20: 10 | G20: =COUNTIFS('V15 - Secure Coding and Archite'!$F$2:$F$26,"Compliant",'V15 - Secure Coding and Archite'!$E$2:$E$26,2) -> 5 | H20: =IF(F20=0,"",G20/F20) -> 0.5 | I20: 8 | J20: =COUNTIFS('V15 - Secure Coding and Archite'!$F$2:$F$26,"Compliant",'V15 - Secure Coding and Archite'!$E$2:$E$26,3) -> 3 | K20: =IF(I20=0,"",J20/I20) -> 0.375 | L20: =COUNTIF('V15 - Secure Coding and Archite'!$F$2:$F$26,"Compliant") -> 11 | M20: =IF(B20=0,"",L20/B20) -> 0.52380952
A21: V16 – Security Logging and Error Handling | B21: 17 | C21: 0 | D21: =COUNTIFS('V16 - Security Logging and Erro'!E3:E23,"Compliant",'V16 - Security Logging and Erro'!F3:F23,1) -> 0 | E21: =IF(C21=0,"",D21/C21) | F21: 16 | G21: =COUNTIFS('V16 - Security Logging and Erro'!F3:F23,"Compliant",'V16 - Security Logging and Erro'!E3:E23,2) -> 10 | H21: =IF(F21=0,"",G21/F21) -> 0.625 | I21: 1 | J21: =COUNTIFS('V16 - Security Logging and Erro'!F3:F23,"Compliant",'V16 - Security Logging and Erro'!E3:E23,3) -> 0 | K21: =IF(I21=0,"",J21/I21) -> 0 | L21: =COUNTIF('V16 - Security Logging and Erro'!$F$2:$F$23,"Compliant") -> 10 | M21: =IF(B21=0,"",L21/B21) -> 0.58823529
A22: V17 – WebRTC | B22: 12 | C22: 0 | D22: =COUNTIFS('V17 - WebRTC'!E3:E16,"Compliant",'V17 - WebRTC'!F3:F16,1) -> 0 | E22: =IF(C22=0,"",D22/C22) | F22: 7 | G22: =COUNTIFS('V17 - WebRTC'!F3:F16,"Compliant",'V17 - WebRTC'!E3:E16,2) -> 0 | H22: =IF(F22=0,"",G22/F22) -> 0 | I22: 5 | J22: =COUNTIFS('V17 - WebRTC'!F3:F16,"Compliant",'V17 - WebRTC'!E3:E16,3) -> 0 | K22: =IF(I22=0,"",J22/I22) -> 0 | L22: =COUNTIF('V17 - WebRTC'!$F$2:$F$16,"Compliant") -> 0 | M22: =IF(B22=0,"",L22/B22) -> 0
A23: TOTAL | B23: 345 | C23: 70 | D23: =SUM(D6:D22) -> 51 | E23: =IFERROR(AVERAGE(E6:E22),"") -> 0.77153846 | F23: =SUM(F6:F22) -> 183 | G23: =SUM(G6:G22) -> 96 | H23: =IFERROR(AVERAGE(H6:H22),"") -> 0.57747309 | I23: =SUM(I6:I22) -> 92 | J23: =SUM(J6:J22) -> 45 | K23: =IFERROR(AVERAGE(K6:K22),"") -> 0.45885417 | L23: =SUM(L6:L22) -> 192 | M23: =IFERROR(AVERAGE(M6:M22),"") -> 0.60336

Sheet V1 - Encoding and Sanitization
A1: Section ID | B1: Section Name | C1: Req ID | D1: Description | E1: Level | F1: Status | G1: Observations | H1: Reference / Link
A2: V1.1 | B2: Encoding and Sanitization Architecture
A3: V1.1 | B3: Encoding and Sanitization Architecture | C3: V1.1.1 | D3: Verify that input is decoded or unescaped into a canonical form only once, it is only decoded when encoded data in that form is expected, and that this is done before processing the input further, for example it is not performed after input validation or sanitization. | E3: 2 | F3: Compliant | G3: Spring MVC / Jackson decode the HTTP request body into the typed DTO record exactly once. The application performs no manual URL decoding loops or double-decoding of any inbound value. | H3: Spring Boot 3.5 default request pipeline; *Controller.java
A4: V1.1 | B4: Encoding and Sanitization Architecture | C4: V1.1.2 | D4: Verify that the application performs output encoding and escaping either as a final step before being used by the interpreter for which it is intended or by the interpreter itself. | E4: 2 | F4: Compliant | G4: Output JSON is generated by Jackson which encodes/escapes values automatically. Audit-log details are CRLF/control-char-stripped by AuditService.sanitize() before being written. | H4: AuditService.java#sanitize; Spring default ObjectMapper
A5: V1.2 | B5: Injection Prevention
A6: V1.2 | B6: Injection Prevention | C6: V1.2.1 | D6: Verify that output encoding for an HTTP response, HTML document, or XML document is relevant for the context required, such as encoding the relevant characters for HTML elements, HTML attributes, HTML comments, CSS, or HTTP header fields, to avoid changing the message or document structure. | E6: 1 | F6: In Progress | G6: x
A7: V1.2 | B7: Injection Prevention | C7: V1.2.2 | D7: Verify that when dynamically building URLs, untrusted data is encoded according to its context (e.g., URL encoding or base64url encoding for query or path parameters). Ensure that only safe URL protocols are permitted (e.g., disallow javascript: or data:). | E7: 1 | F7: Not Applicable
A8: V1.2 | B8: Injection Prevention | C8: V1.2.3 | D8: Verify that output encoding or escaping is used when dynamically building JavaScript content (including JSON), to avoid changing the message or document structure (to avoid JavaScript and JSON injection). | E8: 1 | F8: Compliant | G8: All responses are JSON serialised by Jackson, which encodes special characters in string values (e.g., quotes, backslashes, control chars). | H8: Spring Boot default Jackson MessageConverter
A9: V1.2 | B9: Injection Prevention | C9: V1.2.4 | D9: Verify that data selection or database queries (e.g., SQL, HQL, NoSQL, Cypher) use parameterized queries, ORMs, entity frameworks, or are otherwise protected from SQL Injection and other database injection attacks. This is also relevant when writing stored procedures. | E9: 1 | F9: Compliant | G9: Persistence goes exclusively through Spring Data JPA repositories with derived methods (findAllByOwnerId, existsByIdAndOwnerId, etc.); there is no native SQL / HQL / JPQL string concatenation anywhere in the codebase. | H9: backend/src/main/java/com/kryptos/**/domain/*Repository.java
A10: V1.2 | B10: Injection Prevention | C10: V1.2.5 | D10: Verify that the application protects against OS command injection and that operating system calls use parameterized OS queries or use contextual command line output encoding. | E10: 1 | F10: Compliant | G10: No OS command invocation exists: there is zero use of Runtime.exec, ProcessBuilder, or Process. All file operations use java.nio.file (Path/Files) and never shell out. | H10: FileHandlingService.java; grep over backend/src/main
A11: V1.2 | B11: Injection Prevention | C11: V1.2.6 | D11: Verify that the application protects against LDAP injection vulnerabilities, or that specific security controls to prevent LDAP injection have been implemented. | E11: 2 | F11: Not Applicable
A12: V1.2 | B12: Injection Prevention | C12: V1.2.7 | D12: Verify that the application is protected against XPath injection attacks by using query parameterization or precompiled queries. | E12: 2 | F12: Not Applicable
A13: V1.2 | B13: Injection Prevention | C13: V1.2.8 | D13: Verify that LaTeX processors are configured securely (such as not using the "--shell-escape" flag) and an allowlist of commands is used to prevent LaTeX injection attacks. | E13: 2 | F13: Not Applicable
A14: V1.2 | B14: Injection Prevention | C14: V1.2.9 | D14: Verify that the application escapes special characters in regular expressions (typically using a backslash) to prevent them from being misinterpreted as metacharacters. | E14: 2 | F14: Compliant | G14: The only regex literals in the codebase are static and non-user-controlled: [\\x00-\\x1F\\x7F] (sanitization), [A-Za-z0-9]{1,8} (extension allowlist). No regex is composed with user input. | H14: AuditService.sanitize; CredentialImportExportService.safe; FileHandlingService.storeUpload
A15: V1.2 | B15: Injection Prevention | C15: V1.2.10 | D15: Verify that the application is protected against CSV and Formula Injection. The application must follow the escaping rules defined in RFC 4180 sections 2.6 and 2.7 when exporting CSV content. Additionally, when exporting to CSV or other spreadsheet formats (such as XLS, XLSX, or ODF), special characters (including '=', '+', '-', '@', '\t' (tab), and '\0' (null character)) must be escaped with a single quote if they appear as the first character in a field value. | E15: 3 | F15: Not Applicable
A16: V1.3 | B16: Sanitization
A17: V1.3 | B17: Sanitization | C17: V1.3.1 | D17: Verify that all untrusted HTML input from WYSIWYG editors or similar is sanitized using a well-known and secure HTML sanitization library or framework feature. | E17: 1 | F17: Not Applicable
A18: V1.3 | B18: Sanitization | C18: V1.3.2 | D18: Verify that the application avoids the use of eval() or other dynamic code execution features such as Spring Expression Language (SpEL). Where there is no alternative, any user input being included must be sanitized before being executed. | E18: 1 | F18: Compliant | G18: No use of Spring Expression Language with user input. @PreAuthorize expressions are literal strings ("hasRole('USER')" etc.). No reflection-based code execution. | H18: All @PreAuthorize sites in backend/src/main/java/com/kryptos/**/api/
A19: V1.3 | B19: Sanitization | C19: V1.3.3 | D19: Verify that data being passed to a potentially dangerous context is sanitized beforehand to enforce safety measures, such as only allowing characters which are safe for this context and trimming input which is too long. | E19: 2 | F19: Compliant | G19: AuditService.sanitize strips control characters and CRLF before persistence; CredentialImportExportService.safe truncates and strips control chars before writing imported strings to JPA. | H19: AuditService.sanitize; CredentialImportExportService.safe; AuditServiceTest.log_shouldSanitizeDetails
A20: V1.3 | B20: Sanitization | C20: V1.3.4 | D20: Verify that user-supplied Scalable Vector Graphics (SVG) scriptable content is validated or sanitized to contain only tags and attributes (such as draw graphics) that are safe for the application, e.g., do not contain scripts and foreignObject. | E20: 2 | F20: Not Applicable
A21: V1.3 | B21: Sanitization | C21: V1.3.5 | D21: Verify that the application sanitizes or disables user-supplied scriptable or expression template language content, such as Markdown, CSS or XSL stylesheets, BBCode, or similar. | E21: 2 | F21: Not Applicable
A22: V1.3 | B22: Sanitization | C22: V1.3.6 | D22: Verify that the application protects against Server-side Request Forgery (SSRF) attacks, by validating untrusted data against an allowlist of protocols, domains, paths and ports and sanitizing potentially dangerous characters before using the data to call another service. | E22: 2 | F22: Compliant | G22: Kryptos performs no outbound HTTP/URL fetches based on user-supplied data. The application has zero SSRF surface: no HTTP client is instantiated with a user-controlled URL, no URL fields exist in any DTO that are dereferenced server-side. | H22: No RestTemplate / WebClient / HttpClient usage anywhere in backend/src/main/java
A23: V1.3 | B23: Sanitization | C23: V1.3.7 | D23: Verify that the application protects against template injection attacks by not allowing templates to be built based on untrusted input. Where there is no alternative, any untrusted input being included dynamically during template creation must be sanitized or strictly validated. | E23: 2 | F23: Compliant | G23: Kryptos has no template engine. There is no Thymeleaf, Freemarker, Velocity, Mustache, or any other templating library declared in pom.xml. Responses are JSON, generated by Jackson. | H23: backend/pom.xml (no template engine dependencies)
A24: V1.3 | B24: Sanitization | C24: V1.3.8 | D24: Verify that the application appropriately sanitizes untrusted input before use in Java Naming and Directory Interface (JNDI) queries and that JNDI is configured securely to prevent JNDI injection attacks. | E24: 2 | F24: Compliant | G24: No JNDI lookup paths exist in the codebase. No InitialContext / Context.lookup() calls. Spring Boot is configured with a direct JDBC DataSource (no JNDI DataSource lookup). | H24: application.properties#spring.datasource.url; SecurityConfig.java
A25: V1.3 | B25: Sanitization | C25: V1.3.9 | D25: Verify that the application sanitizes content before it is sent to memcache to prevent injection attacks. | E25: 2 | F25: Not Applicable
A26: V1.3 | B26: Sanitization | C26: V1.3.10 | D26: Verify that format strings which might resolve in an unexpected or malicious way when used are sanitized before being processed. | E26: 2 | F26: Compliant | G26: Java does not expose C-style format-string vulnerabilities (compiler enforces type safety on String.format placeholders). All String.format calls in the codebase use static literal format strings. | H26: AuditService.java; FileHandlingService.java
A27: V1.3 | B27: Sanitization | C27: V1.3.11 | D27: Verify that the application sanitizes user input before passing to mail systems to protect against SMTP or IMAP injection. | E27: 2 | F27: Not Applicable
A28: V1.3 | B28: Sanitization | C28: V1.3.12 | D28: Verify that regular expressions are free from elements causing exponential backtracking, and ensure untrusted input is sanitized to mitigate ReDoS or Runaway Regex attacks. | E28: 3 | F28: Compliant | G28: The two regex literals in use are ReDoS-safe: [\\x00-\\x1F\\x7F] (single character class) and [A-Za-z0-9]{1,8} (bounded, no nested quantifiers, no alternation). User input is matched, never used to build a pattern. | H28: AuditService.sanitize; FileHandlingService.storeUpload
A29: V1.4 | B29: Memory, String, and Unmanaged Code
A30: V1.4 | B30: Memory, String, and Unmanaged Code | C30: V1.4.1 | D30: Verify that the application uses memory-safe string, safer memory copy and pointer arithmetic to detect or prevent stack, buffer, or heap overflows. | E30: 2 | F30: Compliant | G30: Java is a memory-safe language: no pointer arithmetic, no manual buffer management, no JNI / Unsafe usage. The codebase exclusively uses Java collections and java.nio buffers. | H30: Language-level guarantee; backend/src/main
A31: V1.4 | B31: Memory, String, and Unmanaged Code | C31: V1.4.2 | D31: Verify that sign, range, and input validation techniques are used to prevent integer overflows. | E31: 2 | F31: Compliant | G31: DTOs enforce input ranges via @Size on length-bounded fields (username, email, password, vault names). File-size and record-count limits use long arithmetic with explicit bounds (5 MiB cap, 50 000 lines). Java overflow semantics are well defined. | H31: RegisterRequest.java; CreateVaultRequest.java; FileHandlingService.java
A32: V1.4 | B32: Memory, String, and Unmanaged Code | C32: V1.4.3 | D32: Verify that dynamically allocated memory and resources are released, and that references or pointers to freed memory are removed or set to null to prevent dangling pointers and use-after-free vulnerabilities. | E32: 2 | F32: Not Applicable
A33: V1.5 | B33: Safe Deserialization
A34: V1.5 | B34: Safe Deserialization | C34: V1.5.1 | D34: Verify that the application configures XML parsers to use a restrictive configuration and that unsafe features such as resolving external entities are disabled to prevent XML eXternal Entity (XXE) attacks. | E34: 1 | F34: Not Applicable
A35: V1.5 | B35: Safe Deserialization | C35: V1.5.2 | D35: Verify that deserialization of untrusted data enforces safe input handling, such as using an allowlist of object types or restricting client-defined object types, to prevent deserialization attacks. Deserialization mechanisms that are explicitly defined as insecure must not be used with untrusted input. | E35: 2 | F35: Compliant | G35: Jackson deserialisation uses an explicit target type (ObjectMapper.readValue(..., CredentialExportRecord.class)); polymorphic typing is not enabled, so attacker cannot influence the class instantiated. Java built-in serialization is not used anywhere. | H35: CredentialImportExportService.java#importForOwner
A36: V1.5 | B36: Safe Deserialization | C36: V1.5.3 | D36: Verify that different parsers used in the application for the same data type (e.g., JSON parsers, XML parsers, URL parsers), perform parsing in a consistent way and use the same character encoding mechanism to avoid issues such as JSON Interoperability vulnerabilities or different URI or file parsing behavior being exploited in Remote File Inclusion (RFI) or Server-side Request Forgery (SSRF) attacks. | E36: 3 | F36: Compliant | G36: Only one parser (Jackson) is in use for the only structured data format (JSON). There is no XML, YAML, or alternative JSON parser, so parser-divergence vulnerabilities are not exposed. | H36: backend/pom.xml; CredentialImportExportService.java

Sheet V2 - Validation and Business Lo
A1: Section ID | B1: Section Name | C1: Req ID | D1: Description | E1: Level | F1: Status | G1: Observations | H1: Reference / Link
A2: V2.1 | B2: Validation and Business Logic Documentation
A3: V2.1 | B3: Validation and Business Logic Documentation | C3: V2.1.1 | D3: Verify that the application's documentation defines input validation rules for how to check the validity of data items against an expected structure. This could be common data formats such as credit card numbers, email addresses, telephone numbers, or it could be an internal data format. | E3: 1 | F3: Compliant | G3: Applicable to Kryptos due to diverse data inputs (emails, vault names); need to document strict validation rules for every data field.
A4: V2.1 | B4: Validation and Business Logic Documentation | C4: V2.1.2 | D4: Verify that the application's documentation defines how to validate the logical and contextual consistency of combined data items, such as checking that suburb and ZIP code match. | E4: 2 | F4: Compliant | G4: Applicable to Kryptos due to related data entities (User-Vault-Credential); need to document how logical consistency is validated between these objects.
A5: V2.1 | B5: Validation and Business Logic Documentation | C5: V2.1.3 | D5: Verify that expectations for business logic limits and validations are documented, including both per-user and globally across the application. | E5: 2 | F5: Compliant | G5: Applicable to Kryptos due to resource management; need to document global and per-user limits for vaults and credential entries.
A6: V2.2 | B6: Input Validation
A7: V2.2 | B7: Input Validation | C7: V2.2.1 | D7: Verify that input is validated to enforce business or functional expectations for that input. This should either use positive validation against an allow list of values, patterns, and ranges, or be based on comparing the input to an expected structure and logical limits according to predefined rules. For L1, this can focus on input which is used to make specific business or security decisions. For L2 and up, this should apply to all input. | E7: 1 | F7: Compliant | G7: Implemented via DTO bean validation (@NotBlank, @Email, @Size) on every request record and positive validation on file uploads (extension allowlist [A-Za-z0-9]{1,8} and CRLF stripping in CredentialImportExportService.safe()). | H7: backend/src/main/java/com/kryptos/**/dto/*.java; backend/src/main/java/com/kryptos/filehandling/application/FileHandlingService.java#storeUpload; CredentialControllerTest.create_shouldReturn400_whenServiceNameIsBlank
A8: V2.2 | B8: Input Validation | C8: V2.2.2 | D8: Verify that the application is designed to enforce input validation at a trusted service layer. While client-side validation improves usability and should be encouraged, it must not be relied upon as a security control. | E8: 1 | F8: Compliant | G8: All validation lives in the backend service/controller layer; there is no frontend in scope and no validation is delegated to the client. DTOs are validated via @Valid in controllers; ownership and business invariants are enforced in services. | H8: backend/src/main/java/com/kryptos/**/api/*Controller.java; backend/src/main/java/com/kryptos/**/application/*Service.java
A9: V2.2 | B9: Input Validation | C9: V2.2.3 | D9: Verify that the application ensures that combinations of related data items are reasonable according to the pre-defined rules. | E9: 2 | F9: Compliant | G9: Composite consistency checks: CredentialService.create validates vault ownership before saving (vaultRepository.existsByIdAndOwnerId); TrustedDeviceService.register rejects fingerprints already bound to another user. | H9: backend/src/main/java/com/kryptos/credential/application/CredentialService.java; backend/src/main/java/com/kryptos/trusteddevice/application/TrustedDeviceService.java
A10: V2.3 | B10: Business Logic Security
A11: V2.3 | B11: Business Logic Security | C11: V2.3.1 | D11: Verify that the application will only process business logic flows for the same user in the expected sequential step order and without skipping steps. | E11: 1 | F11: Compliant | G11: Kryptos exposes a stateless REST API; every authenticated request is independently authorized via @PreAuthorize and ownership checks. There are no multi-step server-side flows whose sequence could be bypassed, so step-skipping is not exploitable. | H11: All controllers under backend/src/main/java/com/kryptos/**/api/
A12: V2.3 | B12: Business Logic Security | C12: V2.3.2 | D12: Verify that business logic limits are implemented per the application's documentation to avoid business logic flaws being exploited. | E12: 2 | F12: Compliant | G12: Business-logic limits are implemented in code (5 login attempts → 15 min lockout, 5 imports/min/principal, 5 exports/min/principal, 5 MiB file cap, 50 000 line cap). Formal documentation of these limits is still pending. | H12: backend/src/main/java/com/kryptos/auth/application/AuthService.java; backend/src/main/java/com/kryptos/filehandling/application/ImportExportRateLimiter.java; backend/src/main/java/com/kryptos/filehandling/application/FileHandlingService.java
A13: V2.3 | B13: Business Logic Security | C13: V2.3.3 | D13: Verify that transactions are being used at the business logic level such that either a business logic operation succeeds in its entirety or it is rolled back to the previous correct state. | E13: 2 | F13: Compliant | G13: Every mutating service method is annotated @Transactional, so a partial failure rolls back the operation (e.g., CredentialService.create, VaultService.delete, AuditService.log, CredentialImportExportService.importForOwner). | H13: backend/src/main/java/com/kryptos/**/application/*Service.java
A14: V2.3 | B14: Business Logic Security | C14: V2.3.4 | D14: Verify that business logic level locking mechanisms are used to ensure that limited quantity resources (such as theater seats or delivery slots) cannot be double-booked by manipulating the application's logic. | E14: 2 | F14: Not Applicable
A15: V2.3 | B15: Business Logic Security | C15: V2.3.5 | D15: Verify that high-value business logic flows require multi-user approval to prevent unauthorized or accidental actions. This could include but is not limited to large monetary transfers, contract approvals, access to classified information, or safety overrides in manufacturing. | E15: 3 | F15: Not Applicable
A16: V2.4 | B16: Anti-automation
A17: V2.4 | B17: Anti-automation | C17: V2.4.1 | D17: Verify that anti-automation controls are in place to protect against excessive calls to application functions that could lead to data exfiltration, garbage-data creation, quota exhaustion, rate-limit breaches, denial-of-service, or overuse of costly resources. | E17: 2 | F17: Compliant | G17: Anti-automation: login endpoint enforces 5 attempts/min/principal with a 15 min lockout (AuthService); import/export endpoints enforce 5 requests/min/principal via ImportExportRateLimiter → HTTP 429. | H17: AuthService.java; ImportExportRateLimiter.java; AuthServiceTest.login_shouldLockAccount_afterMaxFailedAttempts; ImportExportRateLimiterTest.tryAcquireExport_allowsFivePerMinute_thenThrottles
A18: V2.4 | B18: Anti-automation | C18: V2.4.2 | D18: Verify that business logic flows require realistic human timing, preventing excessively rapid transaction submissions. | E18: 3 | F18: Compliant | G18: Anti-automation realised through ImportExportRateLimiter (5 req/min/principal on import and export) and AuthService (5 login attempts/min/principal → 15 min lockout). Both implement the "no rapid submissions" intent of the requirement. | H18: AuthService.java; ImportExportRateLimiter.java; ImportExportRateLimiterTest

Sheet V3 - Web Frontend Security
A1: Section ID | B1: Section Name | C1: Req ID | D1: Description | E1: Level | F1: Status | G1: Observations | H1: Reference / Link
A2: V3.1 | B2: Web Frontend Security Documentation
A3: V3.1 | B3: Web Frontend Security Documentation | C3: V3.1.1 | D3: Verify that application documentation states the expected security features that browsers using the application must support (such as HTTPS, HTTP Strict Transport Security (HSTS), Content Security Policy (CSP), and other relevant HTTP security mechanisms). It must also define how the application must behave when some of these features are not available (such as warning the user or blocking access). | E3: 3 | F3: Not Applicable
A4: V3.2 | B4: Unintended Content Interpretation
A5: V3.2 | B5: Unintended Content Interpretation | C5: V3.2.1 | D5: Verify that security controls are in place to prevent browsers from rendering content or functionality in HTTP responses in an incorrect context (e.g., when an API, a user-uploaded file or other resource is requested directly). Possible controls could include: not serving the content unless HTTP request header fields (such as Sec-Fetch-\*) indicate it is the correct context, using the sandbox directive of the Content-Security-Policy header field or using the attachment disposition type in the Content-Disposition header field. | E5: 1 | F5: Not Applicable
A6: V3.2 | B6: Unintended Content Interpretation | C6: V3.2.2 | D6: Verify that content intended to be displayed as text, rather than rendered as HTML, is handled using safe rendering functions (such as createTextNode or textContent) to prevent unintended execution of content such as HTML or JavaScript. | E6: 1 | F6: Not Applicable
A7: V3.2 | B7: Unintended Content Interpretation | C7: V3.2.3 | D7: Verify that the application avoids DOM clobbering when using client-side JavaScript by employing explicit variable declarations, performing strict type checking, avoiding storing global variables on the document object, and implementing namespace isolation. | E7: 3 | F7: Not Applicable
A8: V3.3 | B8: Cookie Setup
A9: V3.3 | B9: Cookie Setup | C9: V3.3.1 | D9: Verify that cookies have the 'Secure' attribute set, and if the '\__Host-' prefix is not used for the cookie name, the '__Secure-' prefix must be used for the cookie name. | E9: 1 | F9: Not Applicable
A10: V3.3 | B10: Cookie Setup | C10: V3.3.2 | D10: Verify that each cookie's 'SameSite' attribute value is set according to the purpose of the cookie, to limit exposure to user interface redress attacks and browser-based request forgery attacks, commonly known as cross-site request forgery (CSRF). | E10: 2 | F10: Not Applicable
A11: V3.3 | B11: Cookie Setup | C11: V3.3.3 | D11: Verify that cookies have the '__Host-' prefix for the cookie name unless they are explicitly designed to be shared with other hosts. | E11: 2 | F11: Not Applicable
A12: V3.3 | B12: Cookie Setup | C12: V3.3.4 | D12: Verify that if the value of a cookie is not meant to be accessible to client-side scripts (such as a session token), the cookie must have the 'HttpOnly' attribute set and the same value (e. g. session token) must only be transferred to the client via the 'Set-Cookie' header field. | E12: 2 | F12: Not Applicable
A13: V3.3 | B13: Cookie Setup | C13: V3.3.5 | D13: Verify that when the application writes a cookie, the cookie name and value length combined are not over 4096 bytes. Overly large cookies will not be stored by the browser and therefore not sent with requests, preventing the user from using application functionality which relies on that cookie. | E13: 3 | F13: Not Applicable
A14: V3.4 | B14: Browser Security Mechanism Headers
A15: V3.4 | B15: Browser Security Mechanism Headers | C15: V3.4.1 | D15: Verify that a Strict-Transport-Security header field is included on all responses to enforce an HTTP Strict Transport Security (HSTS) policy. A maximum age of at least 1 year must be defined, and for L2 and up, the policy must apply to all subdomains as well. | E15: 1 | F15: Not Applicable
A16: V3.4 | B16: Browser Security Mechanism Headers | C16: V3.4.2 | D16: Verify that the Cross-Origin Resource Sharing (CORS) Access-Control-Allow-Origin header field is a fixed value by the application, or if the Origin HTTP request header field value is used, it is validated against an allowlist of trusted origins. When 'Access-Control-Allow-Origin: *' needs to be used, verify that the response does not include any sensitive information. | E16: 1 | F16: Not Applicable
A17: V3.4 | B17: Browser Security Mechanism Headers | C17: V3.4.3 | D17: Verify that HTTP responses include a Content-Security-Policy response header field which defines directives to ensure the browser only loads and executes trusted content or resources, in order to limit execution of malicious JavaScript. As a minimum, a global policy must be used which includes the directives object-src 'none' and base-uri 'none' and defines either an allowlist or uses nonces or hashes. For an L3 application, a per-response policy with nonces or hashes must be defined. | E17: 2 | F17: Not Applicable
A18: V3.4 | B18: Browser Security Mechanism Headers | C18: V3.4.4 | D18: Verify that all HTTP responses contain an 'X-Content-Type-Options: nosniff' header field. This instructs browsers not to use content sniffing and MIME type guessing for the given response, and to require the response's Content-Type header field value to match the destination resource. For example, the response to a request for a style is only accepted if the response's Content-Type is 'text/css'. This also enables the use of the Cross-Origin Read Blocking (CORB) functionality by the browser. | E18: 2 | F18: Not Applicable
A19: V3.4 | B19: Browser Security Mechanism Headers | C19: V3.4.5 | D19: Verify that the application sets a referrer policy to prevent leakage of technically sensitive data to third-party services via the 'Referer' HTTP request header field. This can be done using the Referrer-Policy HTTP response header field or via HTML element attributes. Sensitive data could include path and query data in the URL, and for internal non-public applications also the hostname. | E19: 2 | F19: Not Applicable
A20: V3.4 | B20: Browser Security Mechanism Headers | C20: V3.4.6 | D20: Verify that the web application uses the frame-ancestors directive of the Content-Security-Policy header field for every HTTP response to ensure that it cannot be embedded by default and that embedding of specific resources is allowed only when necessary. Note that the X-Frame-Options header field, although supported by browsers, is obsolete and may not be relied upon. | E20: 2 | F20: Not Applicable
A21: V3.4 | B21: Browser Security Mechanism Headers | C21: V3.4.7 | D21: Verify that the Content-Security-Policy header field specifies a location to report violations. | E21: 3 | F21: Not Applicable
A22: V3.4 | B22: Browser Security Mechanism Headers | C22: V3.4.8 | D22: Verify that all HTTP responses that initiate a document rendering (such as responses with Content-Type text/html), include the Cross‑Origin‑Opener‑Policy header field with the same-origin directive or the same-origin-allow-popups directive as required. This prevents attacks that abuse shared access to Window objects, such as tabnabbing and frame counting. | E22: 3 | F22: Not Applicable
A23: V3.5 | B23: Browser Origin Separation
A24: V3.5 | B24: Browser Origin Separation | C24: V3.5.1 | D24: Verify that, if the application does not rely on the CORS preflight mechanism to prevent disallowed cross-origin requests to use sensitive functionality, these requests are validated to ensure they originate from the application itself. This may be done by using and validating anti-forgery tokens or requiring extra HTTP header fields that are not CORS-safelisted request-header fields. This is to defend against browser-based request forgery attacks, commonly known as cross-site request forgery (CSRF). | E24: 1 | F24: Not Applicable
A25: V3.5 | B25: Browser Origin Separation | C25: V3.5.2 | D25: Verify that, if the application relies on the CORS preflight mechanism to prevent disallowed cross-origin use of sensitive functionality, it is not possible to call the functionality with a request which does not trigger a CORS-preflight request. This may require checking the values of the 'Origin' and 'Content-Type' request header fields or using an extra header field that is not a CORS-safelisted header-field. | E25: 1 | F25: Not Applicable
A26: V3.5 | B26: Browser Origin Separation | C26: V3.5.3 | D26: Verify that HTTP requests to sensitive functionality use appropriate HTTP methods such as POST, PUT, PATCH, or DELETE, and not methods defined by the HTTP specification as "safe" such as HEAD, OPTIONS, or GET. Alternatively, strict validation of the Sec-Fetch-* request header fields can be used to ensure that the request did not originate from an inappropriate cross-origin call, a navigation request, or a resource load (such as an image source) where this is not expected. | E26: 1 | F26: Not Applicable
A27: V3.5 | B27: Browser Origin Separation | C27: V3.5.4 | D27: Verify that separate applications are hosted on different hostnames to leverage the restrictions provided by same-origin policy, including how documents or scripts loaded by one origin can interact with resources from another origin and hostname-based restrictions on cookies. | E27: 2 | F27: Not Applicable
A28: V3.5 | B28: Browser Origin Separation | C28: V3.5.5 | D28: Verify that messages received by the postMessage interface are discarded if the origin of the message is not trusted, or if the syntax of the message is invalid. | E28: 2 | F28: Not Applicable
A29: V3.5 | B29: Browser Origin Separation | C29: V3.5.6 | D29: Verify that JSONP functionality is not enabled anywhere across the application to avoid Cross-Site Script Inclusion (XSSI) attacks. | E29: 3 | F29: Not Applicable
A30: V3.5 | B30: Browser Origin Separation | C30: V3.5.7 | D30: Verify that data requiring authorization is not included in script resource responses, like JavaScript files, to prevent Cross-Site Script Inclusion (XSSI) attacks. | E30: 3 | F30: Not Applicable
A31: V3.5 | B31: Browser Origin Separation | C31: V3.5.8 | D31: Verify that authenticated resources (such as images, videos, scripts, and other documents) can be loaded or embedded on behalf of the user only when intended. This can be accomplished by strict validation of the Sec-Fetch-* HTTP request header fields to ensure that the request did not originate from an inappropriate cross-origin call, or by setting a restrictive Cross-Origin-Resource-Policy HTTP response header field to instruct the browser to block returned content. | E31: 3 | F31: Not Applicable
A32: V3.6 | B32: External Resource Integrity
A33: V3.6 | B33: External Resource Integrity | C33: V3.6.1 | D33: Verify that client-side assets, such as JavaScript libraries, CSS, or web fonts, are only hosted externally (e.g., on a Content Delivery Network) if the resource is static and versioned and Subresource Integrity (SRI) is used to validate the integrity of the asset. If this is not possible, there should be a documented security decision to justify this for each resource. | E33: 3 | F33: Not Applicable
A34: V3.7 | B34: Other Browser Security Considerations
A35: V3.7 | B35: Other Browser Security Considerations | C35: V3.7.1 | D35: Verify that the application only uses client-side technologies which are still supported and considered secure. Examples of technologies which do not meet this requirement include NSAPI plugins, Flash, Shockwave, ActiveX, Silverlight, NACL, or client-side Java applets. | E35: 2 | F35: Not Applicable
A36: V3.7 | B36: Other Browser Security Considerations | C36: V3.7.2 | D36: Verify that the application will only automatically redirect the user to a different hostname or domain (which is not controlled by the application) where the destination appears on an allowlist. | E36: 2 | F36: Not Applicable
A37: V3.7 | B37: Other Browser Security Considerations | C37: V3.7.3 | D37: Verify that the application shows a notification when the user is being redirected to a URL outside of the application's control, with an option to cancel the navigation. | E37: 3 | F37: Not Applicable
A38: V3.7 | B38: Other Browser Security Considerations | C38: V3.7.4 | D38: Verify that the application's top-level domain (e.g., site.tld) is added to the public preload list for HTTP Strict Transport Security (HSTS). This ensures that the use of TLS for the application is built directly into the main browsers, rather than relying only on the Strict-Transport-Security response header field. | E38: 3 | F38: Not Applicable
A39: V3.7 | B39: Other Browser Security Considerations | C39: V3.7.5 | D39: Verify that the application behaves as documented (such as warning the user or blocking access) if the browser used to access the application does not support the expected security features. | E39: 3 | F39: Not Applicable

Sheet V4 - API and Web Service
A1: Section ID | B1: Section Name | C1: Req ID | D1: Description | E1: Level | F1: Status | G1: Observations | H1: Reference / Link
A2: V4.1 | B2: Generic Web Service Security
A3: V4.1 | B3: Generic Web Service Security | C3: V4.1.1 | D3: Verify that every HTTP response with a message body contains a Content-Type header field that matches the actual content of the response, including the charset parameter to specify safe character encoding (e.g., UTF-8, ISO-8859-1) according to IANA Media Types, such as "text/", "/+xml" and "/xml". | E3: 1 | F3: Compliant | G3: Spring Boot defaults to application/json;charset=UTF-8 on JSON responses; the export endpoint explicitly sets Content-Type=application/octet-stream with a Content-Disposition header and X-Content-Type-Options=nosniff. | H3: backend/src/main/java/com/kryptos/filehandling/api/ImportExportController.java#exportCredentials
A4: V4.1 | B4: Generic Web Service Security | C4: V4.1.2 | D4: Verify that only user-facing endpoints (intended for manual web-browser access) automatically redirect from HTTP to HTTPS, while other services or endpoints do not implement transparent redirects. This is to avoid a situation where a client is erroneously sending unencrypted HTTP requests, but since the requests are being automatically redirected to HTTPS, the leakage of sensitive data goes undiscovered. | E4: 2 | F4: Not Applicable
A5: V4.1 | B5: Generic Web Service Security | C5: V4.1.3 | D5: Verify that any HTTP header field used by the application and set by an intermediary layer, such as a load balancer, a web proxy, or a backend-for-frontend service, cannot be overridden by the end-user. Example headers might include X-Real-IP, X-Forwarded-*, or X-User-ID. | E5: 2 | F5: Compliant | G5: The application reads identity exclusively from @AuthenticationPrincipal (set by JwtAuthFilter after verifying the Authorization Bearer token). It does not read X-Forwarded-User / X-User-Id / X-Real-IP or any intermediary-set identity header. Spring Boot default server.forward-headers-strategy is NONE. | H5: JwtAuthFilter.java; SecurityConfig.java; all controllers
A6: V4.1 | B6: Generic Web Service Security | C6: V4.1.4 | D6: Verify that only HTTP methods that are explicitly supported by the application or its API (including OPTIONS during preflight requests) can be used and that unused methods are blocked. | E6: 3 | F6: Compliant | G6: Spring MVC returns 405 by default for HTTP methods that are not mapped, and the only mapped methods per endpoint are explicit (POST/GET/PUT/DELETE/PATCH). An explicit method allowlist filter is not in place. | H6: backend/src/main/java/com/kryptos/**/api/*Controller.java
A7: V4.1 | B7: Generic Web Service Security | C7: V4.1.5 | D7: Verify that per-message digital signatures are used to provide additional assurance on top of transport protections for requests or transactions which are highly sensitive or which traverse a number of systems. | E7: 3 | F7: Compliant | G7: Applicable to Kryptos due to HTTP header management; need to ensure that user input cannot manipulate or override security-relevant response headers.
A8: V4.2 | B8: HTTP Message Structure Validation
A9: V4.2 | B9: HTTP Message Structure Validation | C9: V4.2.1 | D9: Verify that all application components (including load balancers, firewalls, and application servers) determine boundaries of incoming HTTP messages using the appropriate mechanism for the HTTP version to prevent HTTP request smuggling. In HTTP/1.x, if a Transfer-Encoding header field is present, the Content-Length header must be ignored per RFC 2616. When using HTTP/2 or HTTP/3, if a Content-Length header field is present, the receiver must ensure that it is consistent with the length of the DATA frames. | E9: 2 | F9: Compliant | G9: HTTP message boundary parsing is delegated to the Spring Boot embedded Tomcat connector, which correctly handles Content-Length and Transfer-Encoding per RFC 7230 and rejects ambiguous messages by default. | H9: Spring Boot 3.5 embedded Tomcat defaults
A10: V4.2 | B10: HTTP Message Structure Validation | C10: V4.2.2 | D10: Verify that when generating HTTP messages, the Content-Length header field does not conflict with the length of the content as determined by the framing of the HTTP protocol, in order to prevent request smuggling attacks. | E10: 3 | F10: Compliant | G10: Responses are produced by Spring MVC; Content-Length is set automatically to match the serialized body length. No manual Content-Length writes anywhere in the code. | H10: Spring MVC default ResponseBodyEmitter / HttpMessageConverter behaviour
A11: V4.2 | B11: HTTP Message Structure Validation | C11: V4.2.3 | D11: Verify that the application does not send nor accept HTTP/2 or HTTP/3 messages with connection-specific header fields such as Transfer-Encoding to prevent response splitting and header injection attacks. | E11: 3 | F11: Compliant | G11: Tomcat HTTP/2 connector rejects connection-specific header fields per RFC 7540 §8.1.2.2 by default. Application does not synthesise such headers anywhere. | H11: Embedded Tomcat HTTP/2 defaults
A12: V4.2 | B12: HTTP Message Structure Validation | C12: V4.2.4 | D12: Verify that the application only accepts HTTP/2 and HTTP/3 requests where the header fields and values do not contain any CR (\r), LF (\n), or CRLF (\r\n) sequences, to prevent header injection attacks. | E12: 3 | F12: Compliant | G12: CR / LF in header names or values are rejected by Tomcat at the HTTP-parser level. Application does not assemble headers from user input — the only response headers come from controller code with static names + bounded values (Content-Type, Content-Disposition, Cache-Control, X-Content-Type-Options). | H12: ImportExportController.exportCredentials; SecurityConfig.headers(...)
A13: V4.2 | B13: HTTP Message Structure Validation | C13: V4.2.5 | D13: Verify that, if the application (backend or frontend) builds and sends requests, it uses validation, sanitization, or other mechanisms to avoid creating URIs (such as for API calls) or HTTP request header fields (such as Authorization or Cookie), which are too long to be accepted by the receiving component. This could cause a denial of service, such as when sending an overly long request (e.g., a long cookie header field), which results in the server always responding with an error status. | E13: 3 | F13: Compliant | G13: The backend does not build or send outbound HTTP requests on behalf of users. There is no RestTemplate / WebClient / HttpClient usage, so URI- or header-injection on outbound calls is not reachable. | H13: No outbound HTTP client in backend/src/main/java
A14: V4.3 | B14: GraphQL
A15: V4.3 | B15: GraphQL | C15: V4.3.1 | D15: Verify that a query allowlist, depth limiting, amount limiting, or query cost analysis is used to prevent GraphQL or data layer expression Denial of Service (DoS) as a result of expensive, nested queries. | E15: 2 | F15: Not Applicable
A16: V4.3 | B16: GraphQL | C16: V4.3.2 | D16: Verify that GraphQL introspection queries are disabled in the production environment unless the GraphQL API is meant to be used by other parties. | E16: 2 | F16: Not Applicable
A17: V4.4 | B17: WebSocket
A18: V4.4 | B18: WebSocket | C18: V4.4.1 | D18: Verify that WebSocket over TLS (WSS) is used for all WebSocket connections. | E18: 1 | F18: Not Applicable
A19: V4.4 | B19: WebSocket | C19: V4.4.2 | D19: Verify that, during the initial HTTP WebSocket handshake, the Origin header field is checked against a list of origins allowed for the application. | E19: 2 | F19: Not Applicable
A20: V4.4 | B20: WebSocket | C20: V4.4.3 | D20: Verify that, if the application's standard session management cannot be used, dedicated tokens are being used for this, which comply with the relevant Session Management security requirements. | E20: 2 | F20: Not Applicable
A21: V4.4 | B21: WebSocket | C21: V4.4.4 | D21: Verify that dedicated WebSocket session management tokens are initially obtained or validated through the previously authenticated HTTPS session when transitioning an existing HTTPS session to a WebSocket channel. | E21: 2 | F21: Not Applicable

Sheet V5 - File Handling
A1: Section ID | B1: Section Name | C1: Req ID | D1: Description | E1: Level | F1: Status | G1: Observations | H1: Reference / Link
A2: V5.1 | B2: File Handling Documentation
A3: V5.1 | B3: File Handling Documentation | C3: V5.1.1 | D3: Verify that the documentation defines the permitted file types, expected file extensions, and maximum size (including unpacked size) for each upload feature. Additionally, ensure that the documentation specifies how files are made safe for end-users to download and process, such as how the application behaves when a malicious file is detected. | E3: 2 | F3: Compliant | G3: Limits exist in code (5 MiB upload cap → 413, 50 000 line record cap, extension allowlist [A-Za-z0-9]{1,8}, 0600 file perms). A formal upload-feature documentation matrix is still pending. | H3: FileHandlingService.java; ImportExportController.java
A4: V5.2 | B4: File Upload and Content
A5: V5.2 | B5: File Upload and Content | C5: V5.2.1 | D5: Verify that the application will only accept files of a size which it can process without causing a loss of performance or a denial of service attack. | E5: 1 | F5: Compliant | G5: 5 MiB cap enforced both at controller (HTTP 413) and at FileHandlingService.storeUpload; importCredentials caps records at 50 000 lines. | H5: ImportExportController.java#importCredentials (HTTP 413 branch); FileHandlingServiceTest.storeUpload_shouldRejectOversizeFile
A6: V5.2 | B6: File Upload and Content | C6: V5.2.2 | D6: Verify that when the application accepts a file, either on its own or within an archive such as a zip file, it checks if the file extension matches an expected file extension and validates that the contents correspond to the type represented by the extension. This includes, but is not limited to, checking the initial 'magic bytes', performing image re-writing, and using specialized libraries for file content validation. For L1, this can focus just on files which are used to make specific business or security decisions. For L2 and up, this must apply to all files being accepted. | E6: 1 | F6: Compliant | G6: Extensions are filtered against a conservative allowlist ([A-Za-z0-9]{1,8}, lowercased). Content validity is enforced downstream by decrypting and JSON-parsing each line; malformed lines are skipped (importForOwner). | H6: FileHandlingService.java#storeUpload; CredentialImportExportService.java#importForOwner
A7: V5.2 | B7: File Upload and Content | C7: V5.2.3 | D7: Verify that the application checks compressed files (e.g., zip, gz, docx, odt) against maximum allowed uncompressed size and against maximum number of files before uncompressing the file. | E7: 2 | F7: Compliant | G7: Kryptos accepts only newline-delimited .kvault import files; no compressed archives (zip, gz, tar, etc.) are decompressed. The compression-bomb attack surface is therefore absent. Hard caps remain in place: 5 MiB payload (HTTP 413) and 50 000 lines. | H7: ImportExportController#importCredentials; FileHandlingService#importCredentials
A8: V5.2 | B8: File Upload and Content | C8: V5.2.4 | D8: Verify that a file size quota and maximum number of files per user are enforced to ensure that a single user cannot fill up the storage with too many files, or excessively large files. | E8: 3 | F8: Compliant | G8: Files are never retained per user: every upload is parsed and securely wiped within the same request, every export streams a freshly built temp file that is wiped immediately after the response body is written. ImportExportRateLimiter caps both endpoints at 5 requests/min/principal → 429. | H8: CredentialImportExportService#importForOwner/exportForOwner; FileHandlingService#secureDelete; ImportExportRateLimiter
A9: V5.2 | B9: File Upload and Content | C9: V5.2.5 | D9: Verify that the application does not allow uploading compressed files containing symlinks unless this is specifically required (in which case it will be necessary to enforce an allowlist of the files that can be symlinked to). | E9: 3 | F9: Compliant | G9: Compressed archives are not accepted by any endpoint (see V5.2.3); symlink-in-archive cannot be reached because no decompression is performed. | H9: ImportExportController; FileHandlingService
A10: V5.2 | B10: File Upload and Content | C10: V5.2.6 | D10: Verify that the application rejects uploaded images with a pixel size larger than the maximum allowed, to prevent pixel flood attacks. | E10: 3 | F10: Not Applicable
A11: V5.3 | B11: File Storage
A12: V5.3 | B12: File Storage | C12: V5.3.1 | D12: Verify that files uploaded or generated by untrusted input and stored in a public folder, are not executed as server-side program code when accessed directly with an HTTP request. | E12: 1 | F12: Compliant | G12: Files are written to an isolated temp directory (kryptos.storage.temp-dir, 0700) outside any web-served path. No static-file handler is registered on the temp dir, so uploads cannot be served as program code. | H12: FileHandlingService.java#initTempDir; application.properties#kryptos.storage.temp-dir
A13: V5.3 | B13: File Storage | C13: V5.3.2 | D13: Verify that when the application creates file paths for file operations, instead of user-submitted filenames, it uses internally generated or trusted data, or if user-submitted filenames or file metadata must be used, strict validation and sanitization must be applied. This is to protect against path traversal, local or remote file inclusion (LFI, RFI), and server-side request forgery (SSRF) attacks. | E13: 1 | F13: Compliant | G13: User filenames are never used as paths. Uploads are stored as import-<UUID><sanitised-extension>; exports as export-<UUID>.kvault. Path-traversal protection via verifyWithinTempDir. | H13: FileHandlingService.java; FileHandlingServiceTest.storeUpload_sanitisesFilename
A14: V5.3 | B14: File Storage | C14: V5.3.3 | D14: Verify that server-side file processing, such as file decompression, ignores user-provided path information to prevent vulnerabilities such as zip slip. | E14: 3 | F14: Compliant | G14: No server-side decompression occurs. Zip-slip / path-traversal-via-archive is not exposed. The single path-traversal mitigation on the upload path is verifyWithinTempDir(), enforced on every read/write. | H14: FileHandlingService#verifyWithinTempDir; FileHandlingServiceTest.secureDelete_refusesPathOutsideTempDir
A15: V5.4 | B15: File Download
A16: V5.4 | B16: File Download | C16: V5.4.1 | D16: Verify that the application validates or ignores user-submitted filenames, including in a JSON, JSONP, or URL parameter and specifies a filename in the Content-Disposition header field in the response. | E16: 2 | F16: Compliant | G16: Export response sets Content-Disposition: attachment; filename="kryptos-export.kvault" — a fixed server-controlled name. No user-submitted filename is echoed in headers. | H16: ImportExportController.java#exportCredentials
A17: V5.4 | B17: File Download | C17: V5.4.2 | D17: Verify that file names served (e.g., in HTTP response header fields or email attachments) are encoded or sanitized (e.g., following RFC 6266) to preserve document structure and prevent injection attacks. | E17: 2 | F17: Compliant | G17: The Content-Disposition filename is hardcoded and ASCII-only; X-Content-Type-Options: nosniff is also set on the response. | H17: ImportExportController.java#exportCredentials
A18: V5.4 | B18: File Download | C18: V5.4.3 | D18: Verify that files obtained from untrusted sources are scanned by antivirus scanners to prevent serving of known malicious content. | E18: 2 | F18: Compliant | G18: Scanning files from untrusted sources ensures Kryptos does not store or distribute known malware during credential import/export operations.

Sheet V6 - Authentication
A1: Section ID | B1: Section Name | C1: Req ID | D1: Description | E1: Level | F1: Status | G1: Observations | H1: Reference / Link
A2: V6.1 | B2: Authentication Documentation
A3: V6.1 | B3: Authentication Documentation | C3: V6.1.1 | D3: Verify that application documentation defines how controls such as rate limiting, anti-automation, and adaptive response, are used to defend against attacks such as credential stuffing and password brute force. The documentation must make clear how these controls are configured and prevent malicious account lockout. | E3: 1 | F3: Compliant | G3: Rate-limiting / anti-automation controls are implemented (5 attempts/15-min lockout on login; 5 req/min on import/export). A formal "authentication anti-automation controls" documentation entry in the security baseline is still pending. | H3: AuthService.java; ImportExportRateLimiter.java
A4: V6.1 | B4: Authentication Documentation | C4: V6.1.2 | D4: Verify that a list of context-specific words is documented in order to prevent their use in passwords. The list could include permutations of organization names, product names, system identifiers, project codenames, department or role names, and similar. | E4: 2 | F4: Compliant | G4: Defines restricted, context-specific terms in Kryptos so users cannot choose predictable passwords related to the organization, reducing the risk of guessing attacks.
A5: V6.1 | B5: Authentication Documentation | C5: V6.1.3 | D5: Verify that, if the application includes multiple authentication pathways, these are all documented together with the security controls and authentication strength which must be consistently enforced across them. | E5: 2 | F5: Compliant | G5: Kryptos exposes a single authentication pathway (username/email + password → JWT issuance at POST /api/auth/login). No alternative authentication routes (SSO, certificate, API key) exist, so multi-pathway consistency is trivially satisfied. | H5: AuthController.java; AuthService.login
A6: V6.2 | B6: Password Security
A7: V6.2 | B7: Password Security | C7: V6.2.1 | D7: Verify that user set passwords are at least 8 characters in length although a minimum of 15 characters is strongly recommended. | E7: 1 | F7: Compliant | G7: RegisterRequest enforces @Size(min=12) on the password, exceeding the L1 minimum of 8 characters. | H7: backend/src/main/java/com/kryptos/auth/application/dto/RegisterRequest.java
A8: V6.2 | B8: Password Security | C8: V6.2.2 | D8: Verify that users can change their password. | E8: 1 | F8: Compliant | G8: Allows Kryptos users to update their passwords, enabling recovery from potential compromise and maintaining account security.
A9: V6.2 | B9: Password Security | C9: V6.2.3 | D9: Verify that password change functionality requires the user's current and new password. | E9: 1 | F9: Compliant | G9: Requires Kryptos users to provide their current password when setting a new one, preventing unauthorized changes from compromised sessions.
A10: V6.2 | B10: Password Security | C10: V6.2.4 | D10: Verify that passwords submitted during account registration or password change are checked against an available set of, at least, the top 3000 passwords which match the application's password policy, e.g. minimum length. | E10: 1 | F10: Not Applicable
A11: V6.2 | B11: Password Security | C11: V6.2.5 | D11: Verify that passwords of any composition can be used, without rules limiting the type of characters permitted. There must be no requirement for a minimum number of upper or lower case characters, numbers, or special characters. | E11: 1 | F11: Compliant | G11: No character composition rules on passwords; only @Size(min=12). Any combination of characters is accepted. | H11: RegisterRequest.java
A12: V6.2 | B12: Password Security | C12: V6.2.6 | D12: Verify that password input fields use type=password to mask the entry. Applications may allow the user to temporarily view the entire masked password, or the last typed character of the password. | E12: 1 | F12: Compliant | G12: Backend-only project; UI-side password masking (type=password) requires a frontend. This will be addressed when a client UI is integrated.
A13: V6.2 | B13: Password Security | C13: V6.2.7 | D13: Verify that "paste" functionality, browser password helpers, and external password managers are permitted. | E13: 1 | F13: Compliant | G13: Backend-only project; paste / browser password manager support is a frontend concern. Will be revisited when the UI is in scope.
A14: V6.2 | B14: Password Security | C14: V6.2.8 | D14: Verify that the application verifies the user's password exactly as received from the user, without any modifications such as truncation or case transformation. | E14: 1 | F14: Compliant | G14: Passwords are hashed exactly as received (Argon2PasswordEncoder operates on raw UTF-8 bytes); no truncation or case transformation is performed. | H14: SecurityConfig.passwordEncoder(); AuthService.register/login
A15: V6.2 | B15: Password Security | C15: V6.2.9 | D15: Verify that passwords of at least 64 characters are permitted. | E15: 2 | F15: Compliant | G15: RegisterRequest only enforces @Size(min=12); there is no upper bound, so 64+ character passwords are accepted. | H15: RegisterRequest.java
A16: V6.2 | B16: Password Security | C16: V6.2.10 | D16: Verify that a user's password stays valid until it is discovered to be compromised or the user rotates it. The application must not require periodic credential rotation. | E16: 2 | F16: Compliant | G16: No periodic-rotation policy is enforced; passwords remain valid indefinitely until the user changes them or they are flagged as compromised. | H16: UserService.java (no rotation logic)
A17: V6.2 | B17: Password Security | C17: V6.2.11 | D17: Verify that the documented list of context specific words is used to prevent easy to guess passwords being created. | E17: 2 | F17: Compliant | G17: Applies Kryptos’s list of context-specific terms during password creation to block predictable and easily guessable passwords.
A18: V6.2 | B18: Password Security | C18: V6.2.12 | D18: Verify that passwords submitted during account registration or password changes are checked against a set of breached passwords. | E18: 2 | F18: Not Applicable
A19: V6.3 | B19: General Authentication Security
A20: V6.3 | B20: General Authentication Security | C20: V6.3.1 | D20: Verify that controls to prevent attacks such as credential stuffing and password brute force are implemented according to the application's security documentation. | E20: 1 | F20: Compliant | G20: AuthService.login enforces 5 failed attempts/min/principal with a 15 min lockout (AuditAction.LOGIN_FAILED emitted on every failure and on lockout). | H20: AuthService.java; AuthServiceTest.login_shouldLockAccount_afterMaxFailedAttempts
A21: V6.3 | B21: General Authentication Security | C21: V6.3.2 | D21: Verify that default user accounts (e.g., "root", "admin", or "sa") are not present in the application or are disabled. | E21: 1 | F21: Compliant | G21: No bootstrap admin / seed accounts. The first user registered through /api/auth/register is created with Role.USER; ADMIN role can only be granted by an existing ADMIN. | H21: AuthService.register; UserService.updateUserRole
A22: V6.3 | B22: General Authentication Security | C22: V6.3.3 | D22: Verify that either a multi-factor authentication mechanism or a combination of single-factor authentication mechanisms, must be used in order to access the application. For L3, one of the factors must be a hardware-based authentication mechanism which provides compromise and impersonation resistance against phishing attacks while verifying the intent to authenticate by requiring a user-initiated action (such as a button press on a FIDO hardware key or a mobile phone). Relaxing any of the considerations in this requirement requires a fully documented rationale and a comprehensive set of mitigating controls. | E22: 2 | F22: Compliant | G22: Requires Kryptos to use strong multi-factor authentication to reduce the risk of account compromise and phishing-based attacks.
A23: V6.3 | B23: General Authentication Security | C23: V6.3.4 | D23: Verify that, if the application includes multiple authentication pathways, there are no undocumented pathways and that security controls and authentication strength are enforced consistently. | E23: 2 | F23: Compliant | G23: Same as V6.1.3 — exactly one authentication pathway exists, so there are no undocumented alternatives and security strength is enforced consistently (Argon2 + 5/15 lockout + JWT issuance). | H23: AuthController.java
A24: V6.3 | B24: General Authentication Security | C24: V6.3.5 | D24: Verify that users are notified of suspicious authentication attempts (successful or unsuccessful). This may include authentication attempts from an unusual location or client, partially successful authentication (only one of multiple factors), an authentication attempt after a long period of inactivity or a successful authentication after several unsuccessful attempts. | E24: 3 | F24: Compliant | G24: Notifies users of suspicious login activity so they can detect and respond quickly to potential unauthorized access.
A25: V6.3 | B25: General Authentication Security | C25: V6.3.6 | D25: Verify that email is not used as either a single-factor or multi-factor authentication mechanism. | E25: 3 | F25: Not Applicable
A26: V6.3 | B26: General Authentication Security | C26: V6.3.7 | D26: Verify that users are notified after updates to authentication details, such as credential resets or modification of the username or email address. | E26: 3 | F26: Compliant | G26: Alerts users when authentication details are changed, helping them detect and respond to unauthorized account modifications.
A27: V6.3 | B27: General Authentication Security | C27: V6.3.8 | D27: Verify that valid users cannot be deduced from failed authentication challenges, such as by basing on error messages, HTTP response codes, or different response times. Registration and forgot password functionality must also have this protection. | E27: 3 | F27: Compliant | G27: Prevents Kryptos from revealing whether a username exists by ensuring authentication, registration, and recovery responses are uniform, reducing the risk of user enumeration attacks.
A28: V6.4 | B28: Authentication Factor Lifecycle and Recovery
A29: V6.4 | B29: Authentication Factor Lifecycle and Recovery | C29: V6.4.1 | D29: Verify that system generated initial passwords or activation codes are securely randomly generated, follow the existing password policy, and expire after a short period of time or after they are initially used. These initial secrets must not be permitted to become the long term password. | E29: 1 | F29: Compliant | G29: Kryptos does not generate initial passwords or activation codes; users set their own password at registration (validated via @Size(min=12)). The attack surface for predictable system-generated credentials is absent. | H29: AuthService.register; RegisterRequest.java
A30: V6.4 | B30: Authentication Factor Lifecycle and Recovery | C30: V6.4.2 | D30: Verify that password hints or knowledge-based authentication (so-called "secret questions") are not present. | E30: 1 | F30: Compliant | G30: No password hints, security questions, or knowledge-based authentication exist in any DTO, service, or endpoint. Password reset (when added) will follow ASVS guidance. | H30: No such feature in backend/src/main/java
A31: V6.4 | B31: Authentication Factor Lifecycle and Recovery | C31: V6.4.3 | D31: Verify that a secure process for resetting a forgotten password is implemented, that does not bypass any enabled multi-factor authentication mechanisms. | E31: 2 | F31: Compliant | G31: Requires Kryptos to implement a secure password reset process that preserves MFA protections, preventing attackers from bypassing additional authentication factors.
A32: V6.4 | B32: Authentication Factor Lifecycle and Recovery | C32: V6.4.4 | D32: Verify that if a multi-factor authentication factor is lost, evidence of identity proofing is performed at the same level as during enrollment. | E32: 2 | F32: Not Applicable
A33: V6.4 | B33: Authentication Factor Lifecycle and Recovery | C33: V6.4.5 | D33: Verify that renewal instructions for authentication mechanisms which expire are sent with enough time to be carried out before the old authentication mechanism expires, configuring automated reminders if necessary. | E33: 3 | F33: Compliant | G33: Provides users with timely renewal notifications for expiring authentication methods, preventing loss of access and maintaining continuous account security.
A34: V6.4 | B34: Authentication Factor Lifecycle and Recovery | C34: V6.4.6 | D34: Verify that administrative users can initiate the password reset process for the user, but that this does not allow them to change or choose the user's password. This prevents a situation where they know the user's password. | E34: 3 | F34: Compliant | G34: Allows administrators to assist with password resets without ever knowing or setting the user’s actual password, preserving account confidentiality.
A35: V6.5 | B35: General Multi-factor authentication requirements
A36: V6.5 | B36: General Multi-factor authentication requirements | C36: V6.5.1 | D36: Verify that lookup secrets, out-of-band authentication requests or codes, and time-based one-time passwords (TOTPs) are only successfully usable once. | E36: 2 | F36: Compliant | G36: Prevents Kryptos from accepting reused authentication codes, reducing replay attacks and protecting account access.
A37: V6.5 | B37: General Multi-factor authentication requirements | C37: V6.5.2 | D37: Verify that, when being stored in the application's backend, lookup secrets with less than 112 bits of entropy (19 random alphanumeric characters or 34 random digits) are hashed with an approved password storage hashing algorithm that incorporates a 32-bit random salt. A standard hash function can be used if the secret has 112 bits of entropy or more. | E37: 2 | F37: Compliant | G37: Requires Kryptos to store lower-entropy lookup secrets securely with salted password hashing, reducing the risk of secret disclosure if backend data is compromised.
A38: V6.5 | B38: General Multi-factor authentication requirements | C38: V6.5.3 | D38: Verify that lookup secrets, out-of-band authentication code, and time-based one-time password seeds, are generated using a Cryptographically Secure Pseudorandom Number Generator (CSPRNG) to avoid predictable values. | E38: 2 | F38: Not Applicable
A39: V6.5 | B39: General Multi-factor authentication requirements | C39: V6.5.4 | D39: Verify that lookup secrets and out-of-band authentication codes have a minimum of 20 bits of entropy (typically 4 random alphanumeric characters or 6 random digits is sufficient). | E39: 2 | F39: Not Applicable
A40: V6.5 | B40: General Multi-factor authentication requirements | C40: V6.5.5 | D40: Verify that out-of-band authentication requests, codes, or tokens, as well as time-based one-time passwords (TOTPs) have a defined lifetime. Out of band requests must have a maximum lifetime of 10 minutes and for TOTP a maximum lifetime of 30 seconds. | E40: 2 | F40: Compliant | G40: Defines short lifetimes for authentication codes in Kryptos to limit their validity window and reduce the risk of interception or reuse.
A41: V6.5 | B41: General Multi-factor authentication requirements | C41: V6.5.6 | D41: Verify that any authentication factor (including physical devices) can be revoked in case of theft or other loss. | E41: 3 | F41: Compliant | G41: Allows revoking compromised authentication factors, preventing unauthorized access if a device or credential is lost or stolen.
A42: V6.5 | B42: General Multi-factor authentication requirements | C42: V6.5.7 | D42: Verify that biometric authentication mechanisms are only used as secondary factors together with either something you have or something you know. | E42: 3 | F42: Not Applicable
A43: V6.5 | B43: General Multi-factor authentication requirements | C43: V6.5.8 | D43: Verify that time-based one-time passwords (TOTPs) are checked based on a time source from a trusted service and not from an untrusted or client provided time. | E43: 3 | F43: Compliant | G43: Uses a trusted server-side time source in Kryptos for TOTP validation, preventing manipulation of authentication by altering client-side time.
A44: V6.6 | B44: Out-of-Band authentication mechanisms
A45: V6.6 | B45: Out-of-Band authentication mechanisms | C45: V6.6.1 | D45: Verify that authentication mechanisms using the Public Switched Telephone Network (PSTN) to deliver One-time Passwords (OTPs) via phone or SMS are offered only when the phone number has previously been validated, alternate stronger methods (such as Time based One-time Passwords) are also offered, and the service provides information on their security risks to users. For L3 applications, phone and SMS must not be available as options. | E45: 2 | F45: Not Applicable
A46: V6.6 | B46: Out-of-Band authentication mechanisms | C46: V6.6.2 | D46: Verify that out-of-band authentication requests, codes, or tokens are bound to the original authentication request for which they were generated and are not usable for a previous or subsequent one. | E46: 2 | F46: Not Applicable
A47: V6.6 | B47: Out-of-Band authentication mechanisms | C47: V6.6.3 | D47: Verify that a code based out-of-band authentication mechanism is protected against brute force attacks by using rate limiting. Consider also using a code with at least 64 bits of entropy. | E47: 2 | F47: Not Applicable
A48: V6.6 | B48: Out-of-Band authentication mechanisms | C48: V6.6.4 | D48: Verify that, where push notifications are used for multi-factor authentication, rate limiting is used to prevent push bombing attacks. Number matching may also mitigate this risk. | E48: 3 | F48: Not Applicable
A49: V6.7 | B49: Cryptographic authentication mechanism
A50: V6.7 | B50: Cryptographic authentication mechanism | C50: V6.7.1 | D50: Verify that the certificates used to verify cryptographic authentication assertions are stored in a way protects them from modification. | E50: 3 | F50: Not Applicable
A51: V6.7 | B51: Cryptographic authentication mechanism | C51: V6.7.2 | D51: Verify that the challenge nonce is at least 64 bits in length, and statistically unique or unique over the lifetime of the cryptographic device. | E51: 3 | F51: Not Applicable
A52: V6.8 | B52: Authentication with an Identity Provider
A53: V6.8 | B53: Authentication with an Identity Provider | C53: V6.8.1 | D53: Verify that, if the application supports multiple identity providers (IdPs), the user's identity cannot be spoofed via another supported identity provider (eg. by using the same user identifier). The standard mitigation would be for the application to register and identify the user using a combination of the IdP ID (serving as a namespace) and the user's ID in the IdP. | E53: 2 | F53: Not Applicable
A54: V6.8 | B54: Authentication with an Identity Provider | C54: V6.8.2 | D54: Verify that the presence and integrity of digital signatures on authentication assertions (for example on JWTs or SAML assertions) are always validated, rejecting any assertions that are unsigned or have invalid signatures. | E54: 2 | F54: Not Applicable
A55: V6.8 | B55: Authentication with an Identity Provider | C55: V6.8.3 | D55: Verify that SAML assertions are uniquely processed and used only once within the validity period to prevent replay attacks. | E55: 2 | F55: Not Applicable
A56: V6.8 | B56: Authentication with an Identity Provider | C56: V6.8.4 | D56: Verify that, if an application uses a separate Identity Provider (IdP) and expects specific authentication strength, methods, or recentness for specific functions, the application verifies this using the information returned by the IdP. For example, if OIDC is used, this might be achieved by validating ID Token claims such as 'acr', 'amr', and 'auth_time' (if present). If the IdP does not provide this information, the application must have a documented fallback approach that assumes that the minimum strength authentication mechanism was used (for example, single-factor authentication using username and password). | E56: 2 | F56: Not Applicable

Sheet V7 - Session Management
A1: Section ID | B1: Section Name | C1: Req ID | D1: Description | E1: Level | F1: Status | G1: Observations | H1: Reference / Link
A2: V7.1 | B2: Session Management Documentation
A3: V7.1 | B3: Session Management Documentation | C3: V7.1.1 | D3: Verify that the user's session inactivity timeout and absolute maximum session lifetime are documented, are appropriate in combination with other controls, and that the documentation includes justification for any deviations from NIST SP 800-63B re-authentication requirements. | E3: 2 | F3: Compliant | G3: Session lifetime is configured via JWT_EXPIRATION (default 3600000 ms = 1 h, documented in backend/.env.example). Formal documentation of the rationale and combined-controls analysis is pending. | H3: application.properties#jwt.expiration; backend/.env.example
A4: V7.1 | B4: Session Management Documentation | C4: V7.1.2 | D4: Verify that the documentation defines how many concurrent (parallel) sessions are allowed for one account as well as the intended behaviors and actions to be taken when the maximum number of active sessions is reached. | E4: 2 | F4: Not Applicable
A5: V7.1 | B5: Session Management Documentation | C5: V7.1.3 | D5: Verify that all systems that create and manage user sessions as part of a federated identity management ecosystem (such as SSO systems) are documented along with controls to coordinate session lifetimes, termination, and any other conditions that require re-authentication. | E5: 2 | F5: Not Applicable
A6: V7.2 | B6: Fundamental Session Management Security
A7: V7.2 | B7: Fundamental Session Management Security | C7: V7.2.1 | D7: Verify that the application performs all session token verification using a trusted, backend service. | E7: 1 | F7: Compliant | G7: JwtAuthFilter validates the token on every request against JwtService.isTokenValid (signature, username, expiry). Spring SessionCreationPolicy.STATELESS. | H7: backend/src/main/java/com/kryptos/shared/security/JwtAuthFilter.java; SecurityConfig.java
A8: V7.2 | B8: Fundamental Session Management Security | C8: V7.2.2 | D8: Verify that the application uses either self-contained or reference tokens that are dynamically generated for session management, i.e. not using static API secrets and keys. | E8: 1 | F8: Compliant | G8: JWTs are generated dynamically per login (signed with HS256 over user+role+iat+exp). No static API secret is used as a session token. | H8: JwtService.generateToken; AuthService.login
A9: V7.2 | B9: Fundamental Session Management Security | C9: V7.2.3 | D9: Verify that if reference tokens are used to represent user sessions, they are unique and generated using a cryptographically secure pseudo-random number generator (CSPRNG) and possess at least 128 bits of entropy. | E9: 1 | F9: Compliant | G9: Kryptos uses self-contained JWTs signed with HS256, not opaque reference tokens. The token integrity is guaranteed by the 256-bit HMAC signature (entropy ≥128 bits enforced at startup by JwtService.getSigningKey, which rejects secrets shorter than 32 bytes). | H9: JwtService.java; JwtServiceTest.constructor_shouldThrow_whenSecretIsTooShort
A10: V7.2 | B10: Fundamental Session Management Security | C10: V7.2.4 | D10: Verify that the application generates a new session token on user authentication, including re-authentication, and terminates the current session token. | E10: 1 | F10: Compliant | G10: Generating a new session token upon authentication in Kryptos and invalidating the previous one reduces the risk of session fixation and unauthorized session reuse.
A11: V7.3 | B11: Session Timeout
A12: V7.3 | B12: Session Timeout | C12: V7.3.1 | D12: Verify that there is an inactivity timeout such that re-authentication is enforced according to risk analysis and documented security decisions. | E12: 2 | F12: Compliant | G12: Session timeout is enforced via JWT expiry (default JWT_EXPIRATION = 3 600 000 ms = 1 h). Expired tokens are rejected by JwtService.isTokenValid. | H12: JwtService.isTokenExpired; JwtServiceTest.isTokenValid_shouldReturnFalse_forExpiredToken
A13: V7.3 | B13: Session Timeout | C13: V7.3.2 | D13: Verify that there is an absolute maximum session lifetime such that re-authentication is enforced according to risk analysis and documented security decisions. | E13: 2 | F13: Compliant | G13: Absolute lifetime = JWT exp claim (1 h by default); no refresh-token endpoint exists, so re-auth is required after exp. | H13: JwtService.generateToken; application.properties#jwt.expiration
A14: V7.4 | B14: Session Termination
A15: V7.4 | B15: Session Termination | C15: V7.4.1 | D15: Verify that when session termination is triggered (such as logout or expiration), the application disallows any further use of the session. For reference tokens or stateful sessions, this means invalidating the session data at the application backend. Applications using self-contained tokens will need a solution such as maintaining a list of terminated tokens, disallowing tokens produced before a per-user date and time or rotating a per-user signing key. | E15: 1 | F15: Compliant | G15: Proper session termination in Kryptos ensures that once a session ends, its token can no longer be used, preventing unauthorized reuse or hijacking of expired sessions.
A16: V7.4 | B16: Session Termination | C16: V7.4.2 | D16: Verify that the application terminates all active sessions when a user account is disabled or deleted (such as an employee leaving the company). | E16: 1 | F16: Compliant | G16: Terminating all active sessions when an account is disabled or deleted prevents former users from retaining access to sensitive information.
A17: V7.4 | B17: Session Termination | C17: V7.4.3 | D17: Verify that the application gives the option to terminate all other active sessions after a successful change or removal of any authentication factor (including password change via reset or recovery and, if present, an MFA settings update). | E17: 2 | F17: Not Applicable
A18: V7.4 | B18: Session Termination | C18: V7.4.4 | D18: Verify that all pages that require authentication have easy and visible access to logout functionality. | E18: 2 | F18: Not Applicable
A19: V7.4 | B19: Session Termination | C19: V7.4.5 | D19: Verify that application administrators are able to terminate active sessions for an individual user or for all users. | E19: 2 | F19: Compliant | G19: Allowing administrators to terminate user sessions enables rapid response to security incidents and prevents ongoing unauthorized access.
A20: V7.5 | B20: Defenses Against Session Abuse
A21: V7.5 | B21: Defenses Against Session Abuse | C21: V7.5.1 | D21: Verify that the application requires full re-authentication before allowing modifications to sensitive account attributes which may affect authentication such as email address, phone number, MFA configuration, or other information used in account recovery. | E21: 2 | F21: Compliant | G21: Requiring full re-authentication before changing sensitive account details prevents attackers with a hijacked session from altering authentication or recovery information.
A22: V7.5 | B22: Defenses Against Session Abuse | C22: V7.5.2 | D22: Verify that users are able to view and (having authenticated again with at least one factor) terminate any or all currently active sessions. | E22: 2 | F22: Not Applicable
A23: V7.5 | B23: Defenses Against Session Abuse | C23: V7.5.3 | D23: Verify that the application requires further authentication with at least one factor or secondary verification before performing highly sensitive transactions or operations. | E23: 3 | F23: Not Applicable
A24: V7.6 | B24: Federated Re-authentication
A25: V7.6 | B25: Federated Re-authentication | C25: V7.6.1 | D25: Verify that session lifetime and termination between Relying Parties (RPs) and Identity Providers (IdPs) behave as documented, requiring re-authentication as necessary such as when the maximum time between IdP authentication events is reached. | E25: 2 | F25: Not Applicable
A26: V7.6 | B26: Federated Re-authentication | C26: V7.6.2 | D26: Verify that creation of a session requires either the user's consent or an explicit action, preventing the creation of new application sessions without user interaction. | E26: 2 | F26: Compliant | G26: A session (JWT) is only issued in response to an explicit POST /api/auth/login with valid credentials supplied by the user. There is no implicit / silent session creation path. | H26: AuthController.login; AuthService.login

Sheet V8 - Authorization
A1: Section ID | B1: Section Name | C1: Req ID | D1: Description | E1: Level | F1: Status | G1: Observations | H1: Reference / Link
A2: V8.1 | B2: Authorization Documentation
A3: V8.1 | B3: Authorization Documentation | C3: V8.1.1 | D3: Verify that authorization documentation defines rules for restricting function-level and data-specific access based on consumer permissions and resource attributes. | E3: 1 | F3: Compliant | G3: Authorization rules are implemented via @PreAuthorize on every controller method (function-level) and ownership checks in services (data-level). A consolidated authorization documentation artefact mapping endpoints to roles and ownership rules is still pending. | H3: All controllers; Sprint1/ThreatIdentification.md
A4: V8.1 | B4: Authorization Documentation | C4: V8.1.2 | D4: Verify that authorization documentation defines rules for field-level access restrictions (both read and write) based on consumer permissions and resource attributes. Note that these rules might depend on other attribute values of the relevant data object, such as state or status. | E4: 2 | F4: Compliant | G4: Field-level access is implemented via response DTOs that explicitly omit sensitive fields (CredentialResponse excludes encryptedPassword, UserResponse excludes password hash). Formal field-level access matrix documentation is pending. | H4: CredentialResponse.java; UserResponse.java
A5: V8.1 | B5: Authorization Documentation | C5: V8.1.3 | D5: Verify that the application's documentation defines the environmental and contextual attributes (including but not limited to, time of day, user location, IP address, or device) that are used in the application to make security decisions, including those pertaining to authentication and authorization. | E5: 3 | F5: Not Applicable
A6: V8.1 | B6: Authorization Documentation | C6: V8.1.4 | D6: Verify that authentication and authorization documentation defines how environmental and contextual factors are used in decision-making, in addition to function-level, data-specific, and field-level authorization. This should include the attributes evaluated, thresholds for risk, and actions taken (e.g., allow, challenge, deny, step-up authentication). | E6: 3 | F6: Not Applicable
A7: V8.2 | B7: General Authorization Design
A8: V8.2 | B8: General Authorization Design | C8: V8.2.1 | D8: Verify that the application ensures that function-level access is restricted to consumers with explicit permissions. | E8: 1 | F8: Compliant | G8: Function-level access control via @PreAuthorize on every controller method (USER / ADMIN / AUDITOR / hasAnyRole). @EnableMethodSecurity enforces it at the proxy layer. | H8: All controllers under backend/src/main/java/com/kryptos/**/api/; AuditControllerTest (RBAC 200/401)
A9: V8.2 | B9: General Authorization Design | C9: V8.2.2 | D9: Verify that the application ensures that data-specific access is restricted to consumers with explicit permissions to specific data items to mitigate insecure direct object reference (IDOR) and broken object level authorization (BOLA). | E9: 1 | F9: Compliant | G9: IDOR mitigations: every read/write on Vault, Credential and TrustedDevice is scoped by ownerId in the repository query or checked via existsByIdAndOwnerId / fingerprint ownership. IDOR negative tests exist for each aggregate. | H9: VaultServiceTest.findById_shouldThrow_whenVaultDoesNotBelongToOwner; CredentialServiceTest.create/findById/delete_shouldThrow_whenCredentialDoesNotBelongToOwner; TrustedDeviceServiceTest.findById_shouldThrowNotFound_whenCallerIsNotOwner_idorSafe
A10: V8.2 | B10: General Authorization Design | C10: V8.2.3 | D10: Verify that the application ensures that field-level access is restricted to consumers with explicit permissions to specific fields to mitigate broken object property level authorization (BOPLA). | E10: 2 | F10: Compliant | G10: Response DTOs deliberately omit sensitive fields: CredentialResponse excludes encryptedPassword; UserResponse excludes the password hash. Request DTOs (records) whitelist only the fields the caller is allowed to set. | H10: CredentialResponse.java; UserResponse.java; UpdateRoleRequest.java; RegisterRequest.java
A11: V8.2 | B11: General Authorization Design | C11: V8.2.4 | D11: Verify that adaptive security controls based on a consumer's environmental and contextual attributes (such as time of day, location, IP address, or device) are implemented for authentication and authorization decisions, as defined in the application's documentation. These controls must be applied when the consumer tries to start a new session and also during an existing session. | E11: 3 | F11: Compliant | G11: Partially applicable, since Kryptos includes trusted device management and auditing features that could support contextual controls, but adaptive authentication based on factors like location or time is not explicitly described.
A12: V8.3 | B12: Operation Level Authorization
A13: V8.3 | B13: Operation Level Authorization | C13: V8.3.1 | D13: Verify that the application enforces authorization rules at a trusted service layer and doesn't rely on controls that an untrusted consumer could manipulate, such as client-side JavaScript. | E13: 1 | F13: Not Applicable
A14: V8.3 | B14: Operation Level Authorization | C14: V8.3.2 | D14: Verify that changes to values on which authorization decisions are made are applied immediately. Where changes cannot be applied immediately, (such as when relying on data in self-contained tokens), there must be mitigating controls to alert when a consumer performs an action when they are no longer authorized to do so and revert the change. Note that this alternative would not mitigate information leakage. | E14: 3 | F14: Compliant | G14: Authorization decisions read claims from the JWT, so changes (e.g., role demotion) only propagate after the token expires. The maximum delay equals JWT_EXPIRATION (1 h by default); documentation of this delay window is pending. | H14: JwtService.generateToken; UserService.updateUserRole; application.properties#jwt.expiration
A15: V8.3 | B15: Operation Level Authorization | C15: V8.3.3 | D15: Verify that access to an object is based on the originating subject's (e.g. consumer's) permissions, not on the permissions of any intermediary or service acting on their behalf. For example, if a consumer calls a web service using a self-contained token for authentication, and the service then requests data from a different service, the second service will use the consumer's token, rather than a machine-to-machine token from the first service, to make permission decisions. | E15: 3 | F15: Compliant | G15: Object access is always decided on the originating subject's permissions: services read the authenticated user via @AuthenticationPrincipal KryptosUserDetails or SecurityContextHolder and pass ownerId into every repository query. No service acts on behalf of another principal. | H15: All controllers; all services
A16: V8.4 | B16: Other Authorization Considerations
A17: V8.4 | B17: Other Authorization Considerations | C17: V8.4.1 | D17: Verify that multi-tenant applications use cross-tenant controls to ensure consumer operations will never affect tenants with which they do not have permissions to interact. | E17: 2 | F17: Not Applicable
A18: V8.4 | B18: Other Authorization Considerations | C18: V8.4.2 | D18: Verify that access to administrative interfaces incorporates multiple layers of security, including continuous consumer identity verification, device security posture assessment, and contextual risk analysis, ensuring that network location or trusted endpoints are not the sole factors for authorization even though they may reduce the likelihood of unauthorized access. | E18: 3 | F18: Not Applicable

Sheet V9 - Self-contained Tokens
A1: Section ID | B1: Section Name | C1: Req ID | D1: Description | E1: Level | F1: Status | G1: Observations | H1: Reference / Link
A2: V9.1 | B2: Token source and integrity
A3: V9.1 | B3: Token source and integrity | C3: V9.1.1 | D3: Verify that self-contained tokens are validated using their digital signature or MAC to protect against tampering before accepting the token's contents. | E3: 1 | F3: Compliant | G3: Token signatures are verified before payload is accepted (Jwts.parser().verifyWith(getSigningKey()).build().parseSignedClaims). Tampered tokens are rejected. | H3: JwtService.extractAllClaims; JwtServiceTest.isTokenValid_shouldReturnFalse_forTamperedToken
A4: V9.1 | B4: Token source and integrity | C4: V9.1.2 | D4: Verify that only algorithms on an allowlist can be used to create and verify self-contained tokens, for a given context. The allowlist must include the permitted algorithms, ideally only either symmetric or asymmetric algorithms, and must not include the 'None' algorithm. If both symmetric and asymmetric must be supported, additional controls will be needed to prevent key confusion. | E4: 1 | F4: Compliant | G4: Only HS256 is used (Jwts.SIG.HS256). jjwt 0.12.6 rejects alg=none by default; an explicit allowlist test is in JwtServiceTest (garbage/tampered token rejection). | H4: JwtService.generateToken; pom.xml#jjwt 0.12.6
A5: V9.1 | B5: Token source and integrity | C5: V9.1.3 | D5: Verify that key material that is used to validate self-contained tokens is from trusted pre-configured sources for the token issuer, preventing attackers from specifying untrusted sources and keys. For JWTs and other JWS structures, headers such as 'jku', 'x5u', and 'jwk' must be validated against an allowlist of trusted sources. | E5: 1 | F5: Compliant | G5: The signing key is derived only from JWT_SECRET (env variable, GitHub repo secret in CI). JwtService.getSigningKey rejects secrets shorter than 32 bytes (IllegalStateException). | H5: JwtService.getSigningKey; JwtServiceTest.constructor_shouldThrow_whenSecretIsTooShort
A6: V9.2 | B6: Token content
A7: V9.2 | B7: Token content | C7: V9.2.1 | D7: Verify that, if a validity time span is present in the token data, the token and its content are accepted only if the verification time is within this validity time span. For example, for JWTs, the claims 'nbf' and 'exp' must be verified. | E7: 1 | F7: Compliant | G7: JwtService.isTokenExpired enforces the exp claim against System.currentTimeMillis(); expired tokens are rejected. | H7: JwtService.isTokenExpired; JwtServiceTest.isTokenValid_shouldReturnFalse_forExpiredToken
A8: V9.2 | B8: Token content | C8: V9.2.2 | D8: Verify that the service receiving a token validates the token to be the correct type and is meant for the intended purpose before accepting the token's contents. For example, only access tokens can be accepted for authorization decisions and only ID Tokens can be used for proving user authentication. | E8: 2 | F8: Compliant | G8: Only one JWT type is issued (an access token with sub + role + iat + exp). There is no separate ID / refresh / authorization token to mis-route, so token-type confusion is not exposed. | H8: JwtService.generateToken
A9: V9.2 | B9: Token content | C9: V9.2.3 | D9: Verify that the service only accepts tokens which are intended for use with that service (audience). For JWTs, this can be achieved by validating the 'aud' claim against an allowlist defined in the service. | E9: 2 | F9: Compliant | G9: JWTs are currently issued without an audience (aud) claim. Adding aud=kryptos at sign time and validating it at verify time is a small, low-risk change targeted for Sprint 3. | H9: JwtService.generateToken / extractAllClaims
A10: V9.2 | B10: Token content | C10: V9.2.4 | D10: Verify that, if a token issuer uses the same private key for issuing tokens to different audiences, the issued tokens contain an audience restriction that uniquely identifies the intended audiences. This will prevent a token from being reused with an unintended audience. If the audience identifier is dynamically provisioned, the token issuer must validate these audiences in order to make sure that they do not result in audience impersonation. | E10: 2 | F10: Not Applicable

Sheet V10 - OAuth and OIDC
A1: Section ID | B1: Section Name | C1: Req ID | D1: Description | E1: Level | F1: Status | G1: Observations | H1: Reference / Link
A2: V10.1 | B2: Generic OAuth and OIDC Security
A3: V10.1 | B3: Generic OAuth and OIDC Security | C3: V10.1.1 | D3: Verify that tokens are only sent to components that strictly need them. For example, when using a backend-for-frontend pattern for browser-based JavaScript applications, access and refresh tokens shall only be accessible for the backend. | E3: 2 | F3: Not Applicable
A4: V10.1 | B4: Generic OAuth and OIDC Security | C4: V10.1.2 | D4: Verify that the client only accepts values from the authorization server (such as the authorization code or ID Token) if these values result from an authorization flow that was initiated by the same user agent session and transaction. This requires that client-generated secrets, such as the proof key for code exchange (PKCE) 'code_verifier', 'state' or OIDC 'nonce', are not guessable, are specific to the transaction, and are securely bound to both the client and the user agent session in which the transaction was started. | E4: 2 | F4: Not Applicable
A5: V10.2 | B5: OAuth Client
A6: V10.2 | B6: OAuth Client | C6: V10.2.1 | D6: Verify that, if the code flow is used, the OAuth client has protection against browser-based request forgery attacks, commonly known as cross-site request forgery (CSRF), which trigger token requests, either by using proof key for code exchange (PKCE) functionality or checking the 'state' parameter that was sent in the authorization request. | E6: 2 | F6: Not Applicable
A7: V10.2 | B7: OAuth Client | C7: V10.2.2 | D7: Verify that, if the OAuth client can interact with more than one authorization server, it has a defense against mix-up attacks. For example, it could require that the authorization server return the 'iss' parameter value and validate it in the authorization response and the token response. | E7: 2 | F7: Not Applicable
A8: V10.2 | B8: OAuth Client | C8: V10.2.3 | D8: Verify that the OAuth client only requests the required scopes (or other authorization parameters) in requests to the authorization server. | E8: 3 | F8: Not Applicable
A9: V10.3 | B9: OAuth Resource Server
A10: V10.3 | B10: OAuth Resource Server | C10: V10.3.1 | D10: Verify that the resource server only accepts access tokens that are intended for use with that service (audience). The audience may be included in a structured access token (such as the 'aud' claim in JWT), or it can be checked using the token introspection endpoint. | E10: 2 | F10: Not Applicable
A11: V10.3 | B11: OAuth Resource Server | C11: V10.3.2 | D11: Verify that the resource server enforces authorization decisions based on claims from the access token that define delegated authorization. If claims such as 'sub', 'scope', and 'authorization_details' are present, they must be part of the decision. | E11: 2 | F11: Compliant | G11: Authorization decisions are derived from the role claim in the JWT (used by the @PreAuthorize hasRole(...) checks via Spring Security). The resource server enforces these decisions on every request through JwtAuthFilter + GlobalMethodSecurity. | H11: JwtAuthFilter.java; SecurityConfig#@EnableMethodSecurity
A12: V10.3 | B12: OAuth Resource Server | C12: V10.3.3 | D12: Verify that if an access control decision requires identifying a unique user from an access token (JWT or related token introspection response), the resource server identifies the user from claims that cannot be reassigned to other users. Typically, it means using a combination of 'iss' and 'sub' claims. | E12: 2 | F12: Not Applicable
A13: V10.3 | B13: OAuth Resource Server | C13: V10.3.4 | D13: Verify that, if the resource server requires specific authentication strength, methods, or recentness, it verifies that the presented access token satisfies these constraints. For example, if present, using the OIDC 'acr', 'amr' and 'auth_time' claims respectively. | E13: 2 | F13: Not Applicable
A14: V10.3 | B14: OAuth Resource Server | C14: V10.3.5 | D14: Verify that the resource server prevents the use of stolen access tokens or replay of access tokens (from unauthorized parties) by requiring sender-constrained access tokens, either Mutual TLS for OAuth 2 or OAuth 2 Demonstration of Proof of Possession (DPoP). | E14: 3 | F14: Not Applicable
A15: V10.4 | B15: OAuth Authorization Server
A16: V10.4 | B16: OAuth Authorization Server | C16: V10.4.1 | D16: Verify that the authorization server validates redirect URIs based on a client-specific allowlist of pre-registered URIs using exact string comparison. | E16: 1 | F16: Not Applicable
A17: V10.4 | B17: OAuth Authorization Server | C17: V10.4.2 | D17: Verify that, if the authorization server returns the authorization code in the authorization response, it can be used only once for a token request. For the second valid request with an authorization code that has already been used to issue an access token, the authorization server must reject a token request and revoke any issued tokens related to the authorization code. | E17: 1 | F17: Not Applicable
A18: V10.4 | B18: OAuth Authorization Server | C18: V10.4.3 | D18: Verify that the authorization code is short-lived. The maximum lifetime can be up to 10 minutes for L1 and L2 applications and up to 1 minute for L3 applications. | E18: 1 | F18: Compliant | G18: Kryptos does not implement an OAuth authorization code flow. No authorization code is issued, so the maximum-lifetime requirement has no surface to violate. | H18: No OAuth in backend/pom.xml or backend/src/main
A19: V10.4 | B19: OAuth Authorization Server | C19: V10.4.4 | D19: Verify that for a given client, the authorization server only allows the usage of grants that this client needs to use. Note that the grants 'token' (Implicit flow) and 'password' (Resource Owner Password Credentials flow) must no longer be used. | E19: 1 | F19: Not Applicable
A20: V10.4 | B20: OAuth Authorization Server | C20: V10.4.5 | D20: Verify that the authorization server mitigates refresh token replay attacks for public clients, preferably using sender-constrained refresh tokens, i.e., Demonstrating Proof of Possession (DPoP) or Certificate-Bound Access Tokens using mutual TLS (mTLS). For L1 and L2 applications, refresh token rotation may be used. If refresh token rotation is used, the authorization server must invalidate the refresh token after usage, and revoke all refresh tokens for that authorization if an already used and invalidated refresh token is provided. | E20: 1 | F20: Compliant | G20: Kryptos does not issue refresh tokens. There is no refresh-token replay surface to mitigate. | H20: JwtService.generateToken (single access-token issuance only)
A21: V10.4 | B21: OAuth Authorization Server | C21: V10.4.6 | D21: Verify that, if the code grant is used, the authorization server mitigates authorization code interception attacks by requiring proof key for code exchange (PKCE). For authorization requests, the authorization server must require a valid 'code_challenge' value and must not accept a 'code_challenge_method' value of 'plain'. For a token request, it must require validation of the 'code_verifier' parameter. | E21: 2 | F21: Not Applicable
A22: V10.4 | B22: OAuth Authorization Server | C22: V10.4.7 | D22: Verify that if the authorization server supports unauthenticated dynamic client registration, it mitigates the risk of malicious client applications. It must validate client metadata such as any registered URIs, ensure the user's consent, and warn the user before processing an authorization request with an untrusted client application. | E22: 2 | F22: Not Applicable
A23: V10.4 | B23: OAuth Authorization Server | C23: V10.4.8 | D23: Verify that refresh tokens have an absolute expiration, including if sliding refresh token expiration is applied. | E23: 2 | F23: Compliant | G23: Kryptos does not issue refresh tokens (see V10.4.5). Access tokens have an absolute expiration (exp claim, default 1 h), enforced on every request. | H23: JwtService.isTokenExpired
A24: V10.4 | B24: OAuth Authorization Server | C24: V10.4.9 | D24: Verify that refresh tokens and reference access tokens can be revoked by an authorized user using the authorization server user interface, to mitigate the risk of malicious clients or stolen tokens. | E24: 2 | F24: Compliant | G24: Kryptos does not issue refresh tokens or opaque reference access tokens; access tokens are self-contained JWTs that simply expire. There is no revocable token-store surface in scope. | H24: JwtService.java
A25: V10.4 | B25: OAuth Authorization Server | C25: V10.4.10 | D25: Verify that confidential client is authenticated for client-to-authorized server backchannel requests such as token requests, pushed authorization requests (PAR), and token revocation requests. | E25: 2 | F25: Not Applicable
A26: V10.4 | B26: OAuth Authorization Server | C26: V10.4.11 | D26: Verify that the authorization server configuration only assigns the required scopes to the OAuth client. | E26: 2 | F26: Not Applicable
A27: V10.4 | B27: OAuth Authorization Server | C27: V10.4.12 | D27: Verify that for a given client, the authorization server only allows the 'response_mode' value that this client needs to use. For example, by having the authorization server validate this value against the expected values or by using pushed authorization request (PAR) or JWT-secured Authorization Request (JAR). | E27: 3 | F27: Not Applicable
A28: V10.4 | B28: OAuth Authorization Server | C28: V10.4.13 | D28: Verify that grant type 'code' is always used together with pushed authorization requests (PAR). | E28: 3 | F28: Not Applicable
A29: V10.4 | B29: OAuth Authorization Server | C29: V10.4.14 | D29: Verify that the authorization server issues only sender-constrained (Proof-of-Possession) access tokens, either with certificate-bound access tokens using mutual TLS (mTLS) or DPoP-bound access tokens (Demonstration of Proof of Possession). | E29: 3 | F29: Not Applicable
A30: V10.4 | B30: OAuth Authorization Server | C30: V10.4.15 | D30: Verify that, for a server-side client (which is not executed on the end-user device), the authorization server ensures that the 'authorization_details' parameter value is from the client backend and that the user has not tampered with it. For example, by requiring the usage of pushed authorization request (PAR) or JWT-secured Authorization Request (JAR). | E30: 3 | F30: Not Applicable
A31: V10.4 | B31: OAuth Authorization Server | C31: V10.4.16 | D31: Verify that the client is confidential and the authorization server requires the use of strong client authentication methods (based on public-key cryptography and resistant to replay attacks), such as mutual TLS ('tls_client_auth', 'self_signed_tls_client_auth') or private key JWT ('private_key_jwt'). | E31: 3 | F31: Not Applicable
A32: V10.5 | B32: OIDC Client
A33: V10.5 | B33: OIDC Client | C33: V10.5.1 | D33: Verify that the client (as the relying party) mitigates ID Token replay attacks. For example, by ensuring that the 'nonce' claim in the ID Token matches the 'nonce' value sent in the authentication request to the OpenID Provider (in OAuth2 refereed to as the authorization request sent to the authorization server). | E33: 2 | F33: Not Applicable
A34: V10.5 | B34: OIDC Client | C34: V10.5.2 | D34: Verify that the client uniquely identifies the user from ID Token claims, usually the 'sub' claim, which cannot be reassigned to other users (for the scope of an identity provider). | E34: 2 | F34: Not Applicable
A35: V10.5 | B35: OIDC Client | C35: V10.5.3 | D35: Verify that the client rejects attempts by a malicious authorization server to impersonate another authorization server through authorization server metadata. The client must reject authorization server metadata if the issuer URL in the authorization server metadata does not exactly match the pre-configured issuer URL expected by the client. | E35: 2 | F35: Not Applicable
A36: V10.5 | B36: OIDC Client | C36: V10.5.4 | D36: Verify that the client validates that the ID Token is intended to be used for that client (audience) by checking that the 'aud' claim from the token is equal to the 'client_id' value for the client. | E36: 2 | F36: Not Applicable
A37: V10.5 | B37: OIDC Client | C37: V10.5.5 | D37: Verify that, when using OIDC back-channel logout, the relying party mitigates denial of service through forced logout and cross-JWT confusion in the logout flow. The client must verify that the logout token is correctly typed with a value of 'logout+jwt', contains the 'event' claim with the correct member name, and does not contain a 'nonce' claim. Note that it is also recommended to have a short expiration (e.g., 2 minutes). | E37: 2 | F37: Not Applicable
A38: V10.6 | B38: OpenID Provider
A39: V10.6 | B39: OpenID Provider | C39: V10.6.1 | D39: Verify that the OpenID Provider only allows values 'code', 'ciba', 'id_token', or 'id_token code' for response mode. Note that 'code' is preferred over 'id_token code' (the OIDC Hybrid flow), and 'token' (any Implicit flow) must not be used. | E39: 2 | F39: Not Applicable
A40: V10.6 | B40: OpenID Provider | C40: V10.6.2 | D40: Verify that the OpenID Provider mitigates denial of service through forced logout. By obtaining explicit confirmation from the end-user or, if present, validating parameters in the logout request (initiated by the relying party), such as the 'id_token_hint'. | E40: 2 | F40: Not Applicable
A41: V10.7 | B41: Consent Management
A42: V10.7 | B42: Consent Management | C42: V10.7.1 | D42: Verify that the authorization server ensures that the user consents to each authorization request. If the identity of the client cannot be assured, the authorization server must always explicitly prompt the user for consent. | E42: 2 | F42: Not Applicable
A43: V10.7 | B43: Consent Management | C43: V10.7.2 | D43: Verify that when the authorization server prompts for user consent, it presents sufficient and clear information about what is being consented to. When applicable, this should include the nature of the requested authorizations (typically based on scope, resource server, Rich Authorization Requests (RAR) authorization details), the identity of the authorized application, and the lifetime of these authorizations. | E43: 2 | F43: Not Applicable
A44: V10.7 | B44: Consent Management | C44: V10.7.3 | D44: Verify that the user can review, modify, and revoke consents which the user has granted through the authorization server. | E44: 2 | F44: Not Applicable

Sheet V11 - Cryptography
A1: Section ID | B1: Section Name | C1: Req ID | D1: Description | E1: Level | F1: Status | G1: Observations | H1: Reference / Link
A2: V11.1 | B2: Cryptographic Inventory and Documentation
A3: V11.1 | B3: Cryptographic Inventory and Documentation | C3: V11.1.1 | D3: Verify that there is a documented policy for management of cryptographic keys and a cryptographic key lifecycle that follows a key management standard such as NIST SP 800-57. This should include ensuring that keys are not overshared (for example, with more than two entities for shared secrets and more than one entity for private keys). | E3: 2 | F3: Compliant | G3: Applicable to Kryptos due to the encryption of credentials at rest, which requires a documented key-management policy.
A4: V11.1 | B4: Cryptographic Inventory and Documentation | C4: V11.1.2 | D4: Verify that a cryptographic inventory is performed, maintained, regularly updated, and includes all cryptographic keys, algorithms, and certificates used by the application. It must also document where keys can and cannot be used in the system, and the types of data that can and cannot be protected using the keys. | E4: 2 | F4: Compliant | G4: Crypto primitives in use can be enumerated from code: AES-256/GCM/NoPadding (EncryptionService), Argon2id (SecurityConfig.passwordEncoder), HS256 (JwtService), SHA-256 (AuditService, EncryptionService key derivation), SecureRandom. A formal cryptographic inventory document is pending. | H4: EncryptionService.java; SecurityConfig.java; JwtService.java; AuditService.java
A5: V11.1 | B5: Cryptographic Inventory and Documentation | C5: V11.1.3 | D5: Verify that cryptographic discovery mechanisms are employed to identify all instances of cryptography in the system, including encryption, hashing, and signing operations. | E5: 3 | F5: Compliant | G5: Applicable to Kryptos due to the full lifecycle that encryption keys must follow.
A6: V11.1 | B6: Cryptographic Inventory and Documentation | C6: V11.1.4 | D6: Verify that a cryptographic inventory is maintained. This must include a documented plan that outlines the migration path to new cryptographic standards, such as post-quantum cryptography, in order to react to future threats. | E6: 3 | F6: Compliant | G6: Applicable to Kryptos due to the presence of several critical secrets that require rotation scheduling.
A7: V11.2 | B7: Secure Cryptography Implementation
A8: V11.2 | B8: Secure Cryptography Implementation | C8: V11.2.1 | D8: Verify that industry-validated implementations (including libraries and hardware-accelerated implementations) are used for cryptographic operations. | E8: 2 | F8: Compliant | G8: Cryptographic operations rely on industry-validated implementations only: JCE (javax.crypto AES/GCM), Spring Security Argon2PasswordEncoder, io.jsonwebtoken (jjwt) 0.12.6, java.security.SecureRandom. | H8: EncryptionService.java; SecurityConfig.passwordEncoder; JwtService.java
A9: V11.2 | B9: Secure Cryptography Implementation | C9: V11.2.2 | D9: Verify that the application is designed with crypto agility such that random number, authenticated encryption, MAC, or hashing algorithms, key lengths, rounds, ciphers and modes can be reconfigured, upgraded, or swapped at any time, to protect against cryptographic breaks. Similarly, it must also be possible to replace keys and passwords and re-encrypt data. This will allow for seamless upgrades to post-quantum cryptography (PQC), once high-assurance implementations of approved PQC schemes or standards are widely available. | E9: 2 | F9: Compliant | G9: Applicable to Kryptos due to the need to upgrade algorithms without rewriting the system.
A10: V11.2 | B10: Secure Cryptography Implementation | C10: V11.2.3 | D10: Verify that all cryptographic primitives utilize a minimum of 128-bits of security based on the algorithm, key size, and configuration. For example, a 256-bit ECC key provides roughly 128 bits of security where RSA requires a 3072-bit key to achieve 128 bits of security. | E10: 2 | F10: Compliant | G10: Cryptographic primitives provide ≥128 bits of security: AES-256 with 128-bit GCM tag, Argon2id with Spring Security defaults, SHA-256. | H10: EncryptionService.java (TAG_LENGTH=128); SecurityConfig.passwordEncoder
A11: V11.2 | B11: Secure Cryptography Implementation | C11: V11.2.4 | D11: Verify that all cryptographic operations are constant-time, with no 'short-circuit' operations in comparisons, calculations, or returns, to avoid leaking information. | E11: 3 | F11: Compliant | G11: Cryptographic operations rely on JCE primitives (Cipher AES/GCM, MessageDigest SHA-256), Argon2PasswordEncoder, and io.jsonwebtoken; all are constant-time at the primitive level. Password verification is delegated to Argon2 .matches(), which performs constant-time comparison. No bespoke byte-by-byte secret comparisons exist in the codebase. | H11: EncryptionService; SecurityConfig.passwordEncoder; AuthService.login
A12: V11.2 | B12: Secure Cryptography Implementation | C12: V11.2.5 | D12: Verify that all cryptographic modules fail securely, and errors are handled in a way that does not enable vulnerabilities, such as Padding Oracle attacks. | E12: 3 | F12: Compliant | G12: Cryptographic failures surface via EncryptionException with a generic message ("Failed to decrypt data"); GCM tag verification fails closed (no plaintext returned). No padding-oracle surface exists because AES/GCM does not use block padding. | H12: EncryptionService.decrypt; EncryptionServiceTest.decrypt_shouldThrow…
A13: V11.3 | B13: Encryption Algorithms
A14: V11.3 | B14: Encryption Algorithms | C14: V11.3.1 | D14: Verify that insecure block modes (e.g., ECB) and weak padding schemes (e.g., PKCS#1 v1.5) are not used. | E14: 1 | F14: Compliant | G14: No insecure block modes or padding schemes are used. Only AES/GCM/NoPadding (authenticated encryption). | H14: EncryptionService.java#ALGORITHM
A15: V11.3 | B15: Encryption Algorithms | C15: V11.3.2 | D15: Verify that only approved ciphers and modes such as AES with GCM are used. | E15: 1 | F15: Compliant | G15: AES-256/GCM/NoPadding is the only symmetric cipher in use (EncryptionService). | H15: EncryptionService.java
A16: V11.3 | B16: Encryption Algorithms | C16: V11.3.3 | D16: Verify that encrypted data is protected against unauthorized modification preferably by using an approved authenticated encryption method or by combining an approved encryption method with an approved MAC algorithm. | E16: 2 | F16: Compliant | G16: Encrypted data is protected by the GCM 128-bit authentication tag. Tampered ciphertext is rejected with EncryptionException at decrypt time. | H16: EncryptionService.decrypt; EncryptionServiceTest.decrypt_shouldThrowEncryptionException_whenCiphertextIsTampered
A17: V11.3 | B17: Encryption Algorithms | C17: V11.3.4 | D17: Verify that nonces, initialization vectors, and other single-use numbers are not used for more than one encryption key and data-element pair. The method of generation must be appropriate for the algorithm being used. | E17: 3 | F17: Compliant | G17: A fresh 12-byte IV is generated from SecureRandom for every encrypt call; two encryptions of the same plaintext produce different ciphertexts (tested). | H17: EncryptionService.encrypt; EncryptionServiceTest.encrypt_shouldProduceDifferentCiphertexts_forSamePlaintext
A18: V11.3 | B18: Encryption Algorithms | C18: V11.3.5 | D18: Verify that any combination of an encryption algorithm and a MAC algorithm is operating in encrypt-then-MAC mode. | E18: 3 | F18: Compliant | G18: AES-GCM is an AEAD mode that internally performs encrypt-then-MAC (ciphertext is computed first, then the GCM authentication tag is computed over IV + AAD + ciphertext). The application never combines encryption + MAC manually. | H18: EncryptionService.encrypt (AES/GCM/NoPadding)
A19: V11.4 | B19: Hashing and Hash-based Functions
A20: V11.4 | B20: Hashing and Hash-based Functions | C20: V11.4.1 | D20: Verify that only approved hash functions are used for general cryptographic use cases, including digital signatures, HMAC, KDF, and random bit generation. Disallowed hash functions, such as MD5, must not be used for any cryptographic purpose. | E20: 1 | F20: Compliant | G20: Only SHA-256 is used (audit-log hash chaining and AES key derivation). MD5/SHA-1 are not used anywhere in the codebase. | H20: AuditService.computeHash; EncryptionService constructor
A21: V11.4 | B21: Hashing and Hash-based Functions | C21: V11.4.2 | D21: Verify that passwords are stored using an approved, computationally intensive, key derivation function (also known as a "password hashing function"), with parameter settings configured based on current guidance. The settings should balance security and performance to make brute-force attacks sufficiently challenging for the required level of security. | E21: 2 | F21: Compliant | G21: Passwords are stored with Argon2PasswordEncoder.defaultsForSpringSecurity_v5_8() (Argon2id with current Spring Security defaults). | H21: SecurityConfig.passwordEncoder
A22: V11.4 | B22: Hashing and Hash-based Functions | C22: V11.4.3 | D22: Verify that hash functions used in digital signatures, as part of data authentication or data integrity are collision resistant and have appropriate bit-lengths. If collision resistance is required, the output length must be at least 256 bits. If only resistance to second pre-image attacks is required, the output length must be at least 128 bits. | E22: 2 | F22: Compliant | G22: SHA-256 is used for the audit hash chain (collision-resistant, 256-bit output). | H22: AuditService.computeHash
A23: V11.4 | B23: Hashing and Hash-based Functions | C23: V11.4.4 | D23: Verify that the application uses approved key derivation functions with key stretching parameters when deriving secret keys from passwords. The parameters in use must balance security and performance to prevent brute-force attacks from compromising the resulting cryptographic key. | E23: 2 | F23: Compliant | G23: The single password-derived secret in the system (user login password) is processed by Argon2id via Argon2PasswordEncoder.defaultsForSpringSecurity_v5_8 — an approved KDF with built-in key stretching. There is no other password-to-key derivation path. | H23: SecurityConfig.passwordEncoder; AuthService.register/login
A24: V11.5 | B24: Random Values
A25: V11.5 | B25: Random Values | C25: V11.5.1 | D25: Verify that all random numbers and strings which are intended to be non-guessable must be generated using a cryptographically secure pseudo-random number generator (CSPRNG) and have at least 128 bits of entropy. Note that UUIDs do not respect this condition. | E25: 2 | F25: Compliant | G25: Non-guessable values are generated via java.security.SecureRandom (CSPRNG): GCM IVs (96 bits — required by GCM), secure-wipe random bytes, and UUID.randomUUID() for filenames. JWTs are signed; no random reference token is issued. | H25: EncryptionService.SECURE_RANDOM; FileHandlingService.secureDelete
A26: V11.5 | B26: Random Values | C26: V11.5.2 | D26: Verify that the random number generation mechanism in use is designed to work securely, even under heavy demand. | E26: 3 | F26: Compliant | G26: java.security.SecureRandom (used for IVs, secure-wipe random bytes and indirectly via UUID.randomUUID()) is designed to degrade gracefully under heavy demand on the JVM platforms Kryptos targets (Linux /dev/urandom-backed SHA1PRNG / NativePRNG). | H26: EncryptionService.SECURE_RANDOM; FileHandlingService.secureDelete
A27: V11.6 | B27: Public Key Cryptography
A28: V11.6 | B28: Public Key Cryptography | C28: V11.6.1 | D28: Verify that only approved cryptographic algorithms and modes of operation are used for key generation and seeding, and digital signature generation and verification. Key generation algorithms must not generate insecure keys vulnerable to known attacks, for example, RSA keys which are vulnerable to Fermat factorization. | E28: 2 | F28: Compliant | G28: AES keys are derived from ENCRYPTION_SECRET via a single SHA-256 pass (EncryptionService constructor). This is functional but is not an approved KDF; migration to HKDF or PBKDF2 is planned. Algorithms for signing (HS256) and hashing (SHA-256) are approved. | H28: EncryptionService constructor
A29: V11.6 | B29: Public Key Cryptography | C29: V11.6.2 | D29: Verify that approved cryptographic algorithms are used for key exchange (such as Diffie-Hellman) with a focus on ensuring that key exchange mechanisms use secure parameters. This will prevent attacks on the key establishment process which could lead to adversary-in-the-middle attacks or cryptographic breaks. | E29: 3 | F29: Not Applicable
A30: V11.7 | B30: In-Use Data Cryptography
A31: V11.7 | B31: In-Use Data Cryptography | C31: V11.7.1 | D31: Verify that full memory encryption is in use that protects sensitive data while it is in use, preventing access by unauthorized users or processes. | E31: 3 | F31: Not Applicable
A32: V11.7 | B32: In-Use Data Cryptography | C32: V11.7.2 | D32: Verify that data minimization ensures the minimal amount of data is exposed during processing, and ensure that data is encrypted immediately after use or as soon as feasible. | E32: 3 | F32: Compliant | G32: Sensitive plaintext lives in memory only for the duration of the operation: passwords are Argon2-hashed before persistence; credential plaintexts are AES-GCM-encrypted before being saved; uploaded byte arrays are zero-filled in CredentialImportExportService.importForOwner finally block; export temp files are 3-pass wiped after the response is written. | H32: AuthService.register; CredentialService.create; CredentialImportExportService.importForOwner; FileHandlingService.secureDelete

Sheet V12 - Secure Communication
A1: Section ID | B1: Section Name | C1: Req ID | D1: Description | E1: Level | F1: Status | G1: Observations | H1: Reference / Link
A2: V12.1 | B2: General TLS Security Guidance
A3: V12.1 | B3: General TLS Security Guidance | C3: V12.1.1 | D3: Verify that only the latest recommended versions of the TLS protocol are enabled, such as TLS 1.2 and TLS 1.3. The latest version of the TLS protocol must be the preferred option. | E3: 1 | F3: Compliant | G3: Applicable to Kryptos due to all API traffic requiring encrypted transport.
A4: V12.1 | B4: General TLS Security Guidance | C4: V12.1.2 | D4: Verify that only recommended cipher suites are enabled, with the strongest cipher suites set as preferred. L3 applications must only support cipher suites which provide forward secrecy. | E4: 2 | F4: Compliant | G4: Applicable to Kryptos due to weak cipher suites posing a downgrade risk.
A5: V12.1 | B5: General TLS Security Guidance | C5: V12.1.3 | D5: Verify that the application validates that mTLS client certificates are trusted before using the certificate identity for authentication or authorization. | E5: 2 | F5: Not Applicable
A6: V12.1 | B6: General TLS Security Guidance | C6: V12.1.4 | D6: Verify that proper certification revocation, such as Online Certificate Status Protocol (OCSP) Stapling, is enabled and configured. | E6: 3 | F6: Compliant | G6: Applicable to Kryptos due to the need to prevent protocol downgrade attacks through HSTS.
A7: V12.1 | B7: General TLS Security Guidance | C7: V12.1.5 | D7: Verify that Encrypted Client Hello (ECH) is enabled in the application's TLS settings to prevent exposure of sensitive metadata, such as the Server Name Indication (SNI), during TLS handshake processes. | E7: 3 | F7: Not Applicable
A8: V12.2 | B8: HTTPS Communication with External Facing Services
A9: V12.2 | B9: HTTPS Communication with External Facing Services | C9: V12.2.1 | D9: Verify that TLS is used for all connectivity between a client and external facing, HTTP-based services, and does not fall back to insecure or unencrypted communications. | E9: 1 | F9: Compliant | G9: HSTS is set via SecurityConfig (includeSubDomains, max-age=31536000), forcing TLS on browser callers. Actual TLS termination is a reverse-proxy responsibility in the target deployment; documentation of the reverse-proxy contract is pending. | H9: SecurityConfig.httpStrictTransportSecurity
A10: V12.2 | B10: HTTPS Communication with External Facing Services | C10: V12.2.2 | D10: Verify that external facing services use publicly trusted TLS certificates. | E10: 1 | F10: Compliant | G10: Applicable to Kryptos due to public clients needing to verify server identity through trusted certificates.
A11: V12.3 | B11: General Service to Service Communication Security
A12: V12.3 | B12: General Service to Service Communication Security | C12: V12.3.1 | D12: Verify that an encrypted protocol such as TLS is used for all inbound and outbound connections to and from the application, including monitoring systems, management tools, remote access and SSH, middleware, databases, mainframes, partner systems, or external APIs. The server must not fall back to insecure or unencrypted protocols. | E12: 2 | F12: Compliant | G12: Applicable to Kryptos due to sensitive data flowing between the API and the database.
A13: V12.3 | B13: General Service to Service Communication Security | C13: V12.3.2 | D13: Verify that TLS clients validate certificates received before communicating with a TLS server. | E13: 2 | F13: Compliant | G13: TLS-validating clients are not yet used: the only outbound connection is JDBC → PostgreSQL on the docker-compose private network, currently without sslmode=verify-full. Switching to verified TLS is on the Sprint 3 backlog. | H13: application.properties#spring.datasource.url; docker-compose.yml
A14: V12.3 | B14: General Service to Service Communication Security | C14: V12.3.3 | D14: Verify that TLS or another appropriate transport encryption mechanism used for all connectivity between internal, HTTP-based services within the application, and does not fall back to insecure or unencrypted communications. | E14: 2 | F14: Compliant | G14: Applicable to Kryptos due to internal service-to-service communication that must also be encrypted.
A15: V12.3 | B15: General Service to Service Communication Security | C15: V12.3.4 | D15: Verify that TLS connections between internal services use trusted certificates. Where internally generated or self-signed certificates are used, the consuming service must be configured to only trust specific internal CAs and specific self-signed certificates. | E15: 2 | F15: Compliant | G15: Applicable to Kryptos due to the possible use of internal CAs for backend services.
A16: V12.3 | B16: General Service to Service Communication Security | C16: V12.3.5 | D16: Verify that services communicating internally within a system (intra-service communications) use strong authentication to ensure that each endpoint is verified. Strong authentication methods, such as TLS client authentication, must be employed to ensure identity, using public-key infrastructure and mechanisms that are resistant to replay attacks. For microservice architectures, consider using a service mesh to simplify certificate management and enhance security. | E16: 3 | F16: Compliant | G16: Applicable to Kryptos due to the highly sensitive traffic between the API and the key store.

Sheet V13 - Configuration
A1: Section ID | B1: Section Name | C1: Req ID | D1: Description | E1: Level | F1: Status | G1: Observations | H1: Reference / Link
A2: V13.1 | B2: Configuration Documentation
A3: V13.1 | B3: Configuration Documentation | C3: V13.1.1 | D3: Verify that all communication needs for the application are documented. This must include external services which the application relies upon and cases where an end user might be able to provide an external location to which the application will then connect. | E3: 2 | F3: Compliant | G3: Applicable to Kryptos due to the need to document all external communication paths.
A4: V13.1 | B4: Configuration Documentation | C4: V13.1.2 | D4: Verify that for each service the application uses, the documentation defines the maximum number of concurrent connections (e.g., connection pool limits) and how the application behaves when that limit is reached, including any fallback or recovery mechanisms, to prevent denial of service conditions. | E4: 3 | F4: Compliant | G4: Applicable to Kryptos due to its dependencies on external components such as the database and the key vault.
A5: V13.1 | B5: Configuration Documentation | C5: V13.1.3 | D5: Verify that the application documentation defines resource‑management strategies for every external system or service it uses (e.g., databases, file handles, threads, HTTP connections). This should include resource‑release procedures, timeout settings, failure handling, and where retry logic is implemented, specifying retry limits, delays, and back‑off algorithms. For synchronous HTTP request–response operations it should mandate short timeouts and either disable retries or strictly limit retries to prevent cascading delays and resource exhaustion. | E5: 3 | F5: Compliant | G5: Applicable to Kryptos due to the sensitive data flows already documented in the threat model.
A6: V13.1 | B6: Configuration Documentation | C6: V13.1.4 | D6: Verify that the application's documentation defines the secrets that are critical for the security of the application and a schedule for rotating them, based on the organization's threat model and business requirements. | E6: 3 | F6: Compliant | G6: Applicable to Kryptos due to the presence of several critical secrets that require rotation scheduling.
A7: V13.2 | B7: Backend Communication Configuration
A8: V13.2 | B8: Backend Communication Configuration | C8: V13.2.1 | D8: Verify that communications between backend application components that don't support the application's standard user session mechanism, including APIs, middleware, and data layers, are authenticated. Authentication must use individual service accounts, short-term tokens, or certificate-based authentication and not unchanging credentials such as passwords, API keys, or shared accounts with privileged access. | E8: 2 | F8: Compliant | G8: The only backend-to-backend channel is JDBC → PostgreSQL, authenticated with DB_USERNAME + DB_PASSWORD (injected from GitHub repo secrets in CI, from .env locally). No anonymous or shared service connection exists. | H8: application.properties#spring.datasource.{username,password}; docker-compose.yml
A9: V13.2 | B9: Backend Communication Configuration | C9: V13.2.2 | D9: Verify that communications between backend application components, including local or operating system services, APIs, middleware, and data layers, are performed with accounts assigned the least necessary privileges. | E9: 2 | F9: Compliant | G9: PostgreSQL is accessed with a single application-level account that has full ownership of the schema. Splitting into per-role accounts (writer / reader / migration) is on the Sprint 3 backlog. | H9: docker-compose.yml#POSTGRES_USER; application.properties#spring.datasource.username
A10: V13.2 | B10: Backend Communication Configuration | C10: V13.2.3 | D10: Verify that if a credential has to be used for service authentication, the credential being used by the consumer is not a default credential (e.g., root/root or admin/admin). | E10: 2 | F10: Compliant | G10: No default credentials are baked into the code or images. DB_PASSWORD, JWT_SECRET, ENCRYPTION_SECRET are mandatory env values; JwtService/EncryptionService fail-fast on missing/weak values. | H10: JwtService.getSigningKey; EncryptionService constructor; backend/.env.example
A11: V13.2 | B11: Backend Communication Configuration | C11: V13.2.4 | D11: Verify that an allowlist is used to define the external resources or systems with which the application is permitted to communicate (e.g., for outbound requests, data loads, or file access). This allowlist can be implemented at the application layer, web server, firewall, or a combination of different layers. | E11: 2 | F11: Compliant | G11: The application makes no outbound HTTP/SMB/FTP requests on behalf of users. There is no outbound resource surface that an allowlist would govern; the JDBC URL is the single hard-coded outbound destination. | H11: No outbound HTTP client in backend/src/main/java
A12: V13.2 | B12: Backend Communication Configuration | C12: V13.2.5 | D12: Verify that the web or application server is configured with an allowlist of resources or systems to which the server can send requests or load data or files from. | E12: 2 | F12: Compliant | G12: Same justification as V13.2.4 — the application does not load data or files from external systems based on user input. The only external endpoint is the JDBC URL, configured via env. | H12: application.properties; SecurityConfig.java
A13: V13.2 | B13: Backend Communication Configuration | C13: V13.2.6 | D13: Verify that where the application connects to separate services, it follows the documented configuration for each connection, such as maximum parallel connections, behavior when maximum allowed connections is reached, connection timeouts, and retry strategies. | E13: 3 | F13: Compliant | G13: Applicable to Kryptos due to internal traffic that must not be trusted implicitly.
A14: V13.3 | B14: Secret Management
A15: V13.3 | B15: Secret Management | C15: V13.3.1 | D15: Verify that a secrets management solution, such as a key vault, is used to securely create, store, control access to, and destroy backend secrets. These could include passwords, key material, integrations with databases and third-party systems, keys and seeds for time-based tokens, other internal secrets, and API keys. Secrets must not be included in application source code or included in build artifacts. For an L3 application, this must involve a hardware-backed solution such as an HSM. | E15: 2 | F15: Compliant | G15: Secrets are stored in GitHub Actions repo secrets (CI) and .env files (local dev). GitHub Secrets are encrypted at rest and access-controlled per repo, but adoption of a dedicated secrets manager (e.g., HashiCorp Vault, AWS Secrets Manager) for the production deployment is still planned. | H15: .github/workflows/ci.yml; backend/.env.example
A16: V13.3 | B16: Secret Management | C16: V13.3.2 | D16: Verify that access to secret assets adheres to the principle of least privilege. | E16: 2 | F16: Compliant | G16: GitHub repo secrets are scoped to the repository: only the CI workflow on protected branches can read them, and they are masked from build logs. Local .env files are 0600 and listed in .gitignore. | H16: .github/workflows/ci.yml; backend/.gitignore
A17: V13.3 | B17: Secret Management | C17: V13.3.3 | D17: Verify that all cryptographic operations are performed using an isolated security module (such as a vault or hardware security module) to securely manage and protect key material from exposure outside of the security module. | E17: 3 | F17: Compliant | G17: Applicable to Kryptos due to cryptographic operations benefiting from running in an isolated trust boundary.
A18: V13.3 | B18: Secret Management | C18: V13.3.4 | D18: Verify that secrets are configured to expire and be rotated based on the application's documentation. | E18: 3 | F18: Compliant | G18: Applicable to Kryptos due to the need for secret rotation over the lifetime of the system.
A19: V13.4 | B19: Unintended Information Leakage
A20: V13.4 | B20: Unintended Information Leakage | C20: V13.4.1 | D20: Verify that the application is deployed either without any source control metadata, including the .git or .svn folders, or in a way that these folders are inaccessible both externally and to the application itself. | E20: 1 | F20: Compliant | G20: The production image is produced by a multi-stage Dockerfile: the final JRE-only stage copies just the built JAR. No .git, no .svn, no source files are shipped. | H20: backend/Dockerfile
A21: V13.4 | B21: Unintended Information Leakage | C21: V13.4.2 | D21: Verify that debug modes are disabled for all components in production environments to prevent exposure of debugging features and information leakage. | E21: 2 | F21: Compliant | G21: Debug surface is disabled in application.properties: spring.jpa.show-sql=false; logging.level.com.kryptos=INFO; logging.level.org.springframework.security=WARN. No Spring Boot Actuator dependency is declared. | H21: backend/src/main/resources/application.properties; backend/pom.xml
A22: V13.4 | B22: Unintended Information Leakage | C22: V13.4.3 | D22: Verify that web servers do not expose directory listings to clients unless explicitly intended. | E22: 2 | F22: Compliant | G22: Spring MVC does not expose directory listings by default and no static resource handler is registered that would expose one. | H22: SecurityConfig.java; KryptosApplication.java
A23: V13.4 | B23: Unintended Information Leakage | C23: V13.4.4 | D23: Verify that using the HTTP TRACE method is not supported in production environments, to avoid potential information leakage. | E23: 2 | F23: Compliant | G23: HTTP TRACE is not registered as a request mapping; Tomcat (Spring Boot default embedded container) disables TRACE by default. | H23: Spring Boot defaults
A24: V13.4 | B24: Unintended Information Leakage | C24: V13.4.5 | D24: Verify that documentation (such as for internal APIs) and monitoring endpoints are not exposed unless explicitly intended. | E24: 2 | F24: Compliant | G24: No documentation or monitoring endpoints are enabled: there is no spring-boot-starter-actuator dependency, no springdoc-openapi dependency, and no Swagger UI bean. The /v3/api-docs/** and /swagger-ui/** SecurityConfig permits resolve to 404 in practice. | H24: backend/pom.xml; SecurityConfig.java
A25: V13.4 | B25: Unintended Information Leakage | C25: V13.4.6 | D25: Verify that the application does not expose detailed version information of backend components. | E25: 3 | F25: Compliant | G25: Spring Boot may emit a Server header by default. Suppressing it via server.server-header= (and verifying via ZAP) is a small Sprint 3 hardening task. | H25: application.properties (no server.server-header configured yet)
A26: V13.4 | B26: Unintended Information Leakage | C26: V13.4.7 | D26: Verify that the web tier is configured to only serve files with specific file extensions to prevent unintentional information, configuration, and source code leakage. | E26: 3 | F26: Compliant | G26: The web tier serves only JSON responses generated by controllers; there is no static-file handler registered, no static directory exposed, and no file-extension-based content serving. | H26: KryptosApplication.java; SecurityConfig.java

Sheet V14 - Data Protection
A1: Section ID | B1: Section Name | C1: Req ID | D1: Description | E1: Level | F1: Status | G1: Observations | H1: Reference / Link
A2: V14.1 | B2: Data Protection Documentation
A3: V14.1 | B3: Data Protection Documentation | C3: V14.1.1 | D3: Verify that all sensitive data created and processed by the application has been identified and classified into protection levels. This includes data that is only encoded and therefore easily decoded, such as Base64 strings or the plaintext payload inside a JWT. Protection levels need to take into account any data protection and privacy regulations and standards which the application is required to comply with. | E3: 2 | F3: Compliant | G3: Highly applicable to Kryptos due to the processing of passwords, credentials, tokens, temporary files, and audit data. Sensitive data should be identified and classified into protection levels according to its confidentiality, integrity, and privacy requirements.
A4: V14.1 | B4: Data Protection Documentation | C4: V14.1.2 | D4: Verify that all sensitive data protection levels have a documented set of protection requirements. This must include (but not be limited to) requirements related to general encryption, integrity verification, retention, how the data is to be logged, access controls around sensitive data in logs, database-level encryption, privacy and privacy-enhancing technologies to be used, and other confidentiality requirements. | E4: 2 | F4: Compliant | G4: Highly applicable to Kryptos. Each sensitive data protection level should have documented protection requirements, including encryption, integrity, retention, logging restrictions, access control, and secure storage in the database and temporary file handling.
A5: V14.2 | B5: General Data Protection
A6: V14.2 | B6: General Data Protection | C6: V14.2.1 | D6: Verify that sensitive data is only sent to the server in the HTTP message body or header fields, and that the URL and query string do not contain sensitive information, such as an API key or session token. | E6: 1 | F6: Compliant | G6: Highly applicable to Kryptos, since credentials and other sensitive authentication-related data must never be included in the URL or query string. A suitable approach is to ensure that such data is sent only in HTTP bodies or secure header fields.
A7: V14.2 | B7: General Data Protection | C7: V14.2.2 | D7: Verify that the application prevents sensitive data from being cached in server components, such as load balancers and application caches, or ensures that the data is securely purged after use. | E7: 2 | F7: Not Applicable
A8: V14.2 | B8: General Data Protection | C8: V14.2.3 | D8: Verify that defined sensitive data is not sent to untrusted parties (e.g., user trackers) to prevent unwanted collection of data outside of the application's control. | E8: 2 | F8: Compliant | G8: Highly applicable to Kryptos, since the system handles highly sensitive information such as credentials and authentication-related data. Sensitive data should never be transmitted to untrusted third parties or external services outside the application's control, in order to avoid unauthorized collection, exposure, or misuse.
A9: V14.2 | B9: General Data Protection | C9: V14.2.4 | D9: Verify that controls around sensitive data related to encryption, integrity verification, retention, how the data is to be logged, access controls around sensitive data in logs, privacy and privacy-enhancing technologies, are implemented as defined in the documentation for the specific data's protection level. | E9: 2 | F9: Compliant | G9: Highly applicable to Kryptos due to the need to protect credentials, authentication-related data, temporary files, and audit records according to their sensitivity. This should be addressed by documenting, for each protection level, the expected controls for encryption, integrity verification, retention, logging restrictions, access control over logged sensitive data, and other privacy-related safeguards.
A10: V14.2 | B10: General Data Protection | C10: V14.2.5 | D10: Verify that caching mechanisms are configured to only cache responses which have the expected content type for that resource and do not contain sensitive, dynamic content. The web server should return a 404 or 302 response when a non-existent file is accessed rather than returning a different, valid file. This should prevent Web Cache Deception attacks. | E10: 3 | F10: Not Applicable
A11: V14.2 | B11: General Data Protection | C11: V14.2.6 | D11: Verify that the application only returns the minimum required sensitive data for the application's functionality. For example, only returning some of the digits of a credit card number and not the full number. If the complete data is required, it should be masked in the user interface unless the user specifically views it. | E11: 3 | F11: Not Applicable
A12: V14.2 | B12: General Data Protection | C12: V14.2.7 | D12: Verify that sensitive information is subject to data retention classification, ensuring that outdated or unnecessary data is deleted automatically, on a defined schedule, or as the situation requires. | E12: 3 | F12: Compliant | G12: Highly applicable to Kryptos, especially due to the handling of temporary files generated during import and export operations, as well as other potentially outdated sensitive records. This requirement should be addressed through defined data retention and deletion policies, including automatic removal schedules where appropriate and secure wipe procedures for temporary sensitive data.
A13: V14.2 | B13: General Data Protection | C13: V14.2.8 | D13: Verify that sensitive information is removed from the metadata of user-submitted files unless storage is consented to by the user. | E13: 3 | F13: Compliant | G13: Highly applicable to Kryptos, especially in import/export workflows. File metadata should be minimized or removed whenever it may expose sensitive information, unless its retention is explicitly required and consented to.
A14: V14.3 | B14: Client-side Data Protection
A15: V14.3 | B15: Client-side Data Protection | C15: V14.3.1 | D15: Verify that authenticated data is cleared from client storage, such as the browser DOM, after the client or session is terminated. The 'Clear-Site-Data' HTTP response header field may be able to help with this but the client-side should also be able to clear up if the server connection is not available when the session is terminated. | E15: 1 | F15: Not Applicable
A16: V14.3 | B16: Client-side Data Protection | C16: V14.3.2 | D16: Verify that the application sets sufficient anti-caching HTTP response header fields (i.e., Cache-Control: no-store) so that sensitive data is not cached in browsers. | E16: 2 | F16: Compliant | G16: The export endpoint sets Cache-Control: no-store and X-Content-Type-Options: nosniff on the credential download. JSON endpoints rely on the browser default of not caching authenticated XHR responses. | H16: ImportExportController.exportCredentials
A17: V14.3 | B17: Client-side Data Protection | C17: V14.3.3 | D17: Verify that data stored in browser storage (such as localStorage, sessionStorage, IndexedDB, or cookies) does not contain sensitive data, with the exception of session tokens. | E17: 2 | F17: Not Applicable

Sheet V15 - Secure Coding and Archite
A1: Section ID | B1: Section Name | C1: Req ID | D1: Description | E1: Level | F1: Status | G1: Observations | H1: Reference / Link
A2: V15.1 | B2: Secure Coding and Architecture Documentation
A3: V15.1 | B3: Secure Coding and Architecture Documentation | C3: V15.1.1 | D3: Verify that application documentation defines risk based remediation time frames for 3rd party component versions with vulnerabilities and for updating libraries in general, to minimize the risk from these components. | E3: 1 | F3: Compliant | G3: Applicable to Kryptos due to the expected use of third-party libraries for backend development, database access, authentication support, file handling, and security-related features. This requirement may be addressed by documenting risk-based remediation time frames for vulnerable components and by defining update priorities according to severity and potential impact on the application.
A4: V15.1 | B4: Secure Coding and Architecture Documentation | C4: V15.1.2 | D4: Verify that an inventory catalog, such as software bill of materials (SBOM), is maintained of all third-party libraries in use, including verifying that components come from pre-defined, trusted, and continually maintained repositories. | E4: 2 | F4: Compliant | G4: backend/pom.xml is the authoritative dependency manifest; OWASP Dependency-Check runs in CI and produces HTML/JSON/XML reports listing every third-party component with version + CVE metadata. A formal CycloneDX SBOM publication is still pending. | H4: .github/workflows/ci.yml#sca; backend/pom.xml
A5: V15.1 | B5: Secure Coding and Architecture Documentation | C5: V15.1.3 | D5: Verify that the application documentation identifies functionality which is time-consuming or resource-demanding. This must include how to prevent a loss of availability due to overusing this functionality and how to avoid a situation where building a response takes longer than the consumer's timeout. Potential defenses may include asynchronous processing, using queues, and limiting parallel processes per user and per application. | E5: 2 | F5: Compliant | G5: Time/resource-intensive operations are identified in code (login lockout window, import/export rate limit, AES-GCM encryption per credential, secure 3-pass wipe). A consolidated documentation entry listing these and their availability protections is pending. | H5: AuthService.java; ImportExportRateLimiter.java; FileHandlingService.java
A6: V15.1 | B6: Secure Coding and Architecture Documentation | C6: V15.1.4 | D6: Verify that application documentation highlights third-party libraries which are considered to be "risky components". | E6: 3 | F6: Compliant | G6: Applicable to Kryptos due to its expected reliance on external libraries for security-sensitive or system-level functionality. This may be addressed by identifying third-party components with elevated risk, such as libraries related to authentication, cryptography, file handling, or operating system interaction, and documenting their risk relevance for future review and monitoring.
A7: V15.1 | B7: Secure Coding and Architecture Documentation | C7: V15.1.5 | D7: Verify that application documentation highlights parts of the application where "dangerous functionality" is being used. | E7: 3 | F7: Compliant | G7: Highly applicable to Kryptos because the application includes sensitive and potentially dangerous functionality, particularly in operating system interaction, temporary file handling, import/export workflows, and secure wipe procedures. This requirement may be addressed by explicitly documenting these high-risk areas and the safeguards expected around their use.
A8: V15.2 | B8: Security Architecture and Dependencies
A9: V15.2 | B9: Security Architecture and Dependencies | C9: V15.2.1 | D9: Verify that the application only contains components which have not breached the documented update and remediation time frames. | E9: 1 | F9: Compliant | G9: OWASP Dependency-Check is integrated in the SAST job (failBuildOnCVSS=9). It currently runs with continue-on-error=true while the backlog is triaged; tightening to fail on CVSS≥7 is on the Sprint 3 list. | H9: .github/workflows/ci.yml#sca; backend/pom.xml#dependency-check-maven
A10: V15.2 | B10: Security Architecture and Dependencies | C10: V15.2.2 | D10: Verify that the application has implemented defenses against loss of availability due to functionality which is time-consuming or resource-demanding, based on the documented security decisions and strategies for this. | E10: 2 | F10: Not Applicable
A11: V15.2 | B11: Security Architecture and Dependencies | C11: V15.2.3 | D11: Verify that the production environment only includes functionality that is required for the application to function, and does not expose extraneous functionality such as test code, sample snippets, and development functionality. | E11: 2 | F11: Compliant | G11: Production build = mvn package output of src/main only. Test code (src/test) is not packaged into the JAR; no sample data is loaded; no debug or developer endpoints are exposed (no actuator dependency). | H11: backend/Dockerfile; backend/pom.xml
A12: V15.2 | B12: Security Architecture and Dependencies | C12: V15.2.4 | D12: Verify that third-party components and all of their transitive dependencies are included from the expected repository, whether internally owned or an external source, and that there is no risk of a dependency confusion attack. | E12: 3 | F12: Not Applicable
A13: V15.2 | B13: Security Architecture and Dependencies | C13: V15.2.5 | D13: Verify that the application implements additional protections around parts of the application which are documented as containing "dangerous functionality" or using third-party libraries considered to be "risky components". This could include techniques such as sandboxing, encapsulation, containerization or network level isolation to delay and deter attackers who compromise one part of an application from pivoting elsewhere in the application. | E13: 3 | F13: Not Applicable
A14: V15.3 | B14: Defensive Coding
A15: V15.3 | B15: Defensive Coding | C15: V15.3.1 | D15: Verify that the application only returns the required subset of fields from a data object. For example, it should not return an entire data object, as some individual fields should not be accessible to users. | E15: 1 | F15: Compliant | G15: Response DTOs select only the fields appropriate for the caller (e.g., CredentialResponse omits encryptedPassword; UserResponse omits password hash). The exception handler returns a generic 500 message with no entity payload. | H15: CredentialResponse.java; UserResponse.java; GlobalExceptionHandler.handleGeneric
A16: V15.3 | B16: Defensive Coding | C16: V15.3.2 | D16: Verify that where the application backend makes calls to external URLs, it is configured to not follow redirects unless it is intended functionality. | E16: 2 | F16: Not Applicable
A17: V15.3 | B17: Defensive Coding | C17: V15.3.3 | D17: Verify that the application has countermeasures to protect against mass assignment attacks by limiting allowed fields per controller and action, e.g., it is not possible to insert or update a field value when it was not intended to be part of that action. | E17: 2 | F17: Compliant | G17: Mass-assignment is structurally impossible: every controller receives a Java record DTO listing exactly the fields the user may set. RegisterRequest exposes (username, email, password) — no role; UpdateRoleRequest exposes only role and is gated by @PreAuthorize hasRole(ADMIN). | H17: RegisterRequest.java; UpdateRoleRequest.java; UserController#updateUserRole
A18: V15.3 | B18: Defensive Coding | C18: V15.3.4 | D18: Verify that all proxying and middleware components transfer the user's original IP address correctly using trusted data fields that cannot be manipulated by the end user, and the application and web server use this correct value for logging and security decisions such as rate limiting, taking into account that even the original IP address may not be reliable due to dynamic IPs, VPNs, or corporate firewalls. | E18: 2 | F18: Not Applicable
A19: V15.3 | B19: Defensive Coding | C19: V15.3.5 | D19: Verify that the application explicitly ensures that variables are of the correct type and performs strict equality and comparator operations. This is to avoid type juggling or type confusion vulnerabilities caused by the application code making an assumption about a variable type. | E19: 2 | F19: Compliant | G19: Java enforces static typing at compile time. Equality comparisons use .equals() for objects (username/email comparisons) and primitive == for primitives. No type juggling is possible. | H19: AuthService.login; UserService.findById; all DTO records
A20: V15.3 | B20: Defensive Coding | C20: V15.3.6 | D20: Verify that JavaScript code is written in a way that prevents prototype pollution, for example, by using Set() or Map() instead of object literals. | E20: 2 | F20: Not Applicable
A21: V15.3 | B21: Defensive Coding | C21: V15.3.7 | D21: Verify that the application has defenses against HTTP parameter pollution attacks, particularly if the application framework makes no distinction about the source of request parameters (query string, body parameters, cookies, or header fields). | E21: 2 | F21: Not Applicable
A22: V15.4 | B22: Safe Concurrency
A23: V15.4 | B23: Safe Concurrency | C23: V15.4.1 | D23: Verify that shared objects in multi-threaded code (such as caches, files, or in-memory objects accessed by multiple threads) are accessed safely by using thread-safe types and synchronization mechanisms like locks or semaphores to avoid race conditions and data corruption. | E23: 3 | F23: Not Applicable
A24: V15.4 | B24: Safe Concurrency | C24: V15.4.2 | D24: Verify that checks on a resource's state, such as its existence or permissions, and the actions that depend on them are performed as a single atomic operation to prevent time-of-check to time-of-use (TOCTOU) race conditions. For example, checking if a file exists before opening it, or verifying a user’s access before granting it. | E24: 3 | F24: Compliant | G24: All check-then-act sequences run inside an @Transactional service method, giving a consistent read-modify-write window (existsByIdAndOwnerId → save inside the same transaction). The file-system check-then-act in FileHandlingService is bounded by a normalised path + CREATE_NEW flag, which fails closed on race. | H24: CredentialService.create; VaultService.delete; FileHandlingService.exportCredentials (CREATE_NEW)
A25: V15.4 | B25: Safe Concurrency | C25: V15.4.3 | D25: Verify that locks are used consistently to avoid threads getting stuck, whether by waiting on each other or retrying endlessly, and that locking logic stays within the code responsible for managing the resource to ensure locks cannot be inadvertently or maliciously modified by external classes or code. | E25: 3 | F25: Not Applicable
A26: V15.4 | B26: Safe Concurrency | C26: V15.4.4 | D26: Verify that resource allocation policies prevent thread starvation by ensuring fair access to resources, such as by leveraging thread pools, allowing lower-priority threads to proceed within a reasonable timeframe. | E26: 3 | F26: Not Applicable

Sheet V16 - Security Logging and Erro
A1: Section ID | B1: Section Name | C1: Req ID | D1: Description | E1: Level | F1: Status | G1: Observations | H1: Reference / Link
A2: V16.1 | B2: Security Logging Documentation
A3: V16.1 | B3: Security Logging Documentation | C3: V16.1.1 | D3: Verify that an inventory exists documenting the logging performed at each layer of the application's technology stack, what events are being logged, log formats, where that logging is stored, how it is used, how access to it is controlled, and for how long logs are kept. | E3: 2 | F3: Compliant | G3: The full set of security events is enumerated in AuditAction (LOGIN, LOGIN_FAILED, REGISTER, CREDENTIAL_*, VAULT_*, USER_*, DEVICE_*, EXPORT, IMPORT, SECURE_WIPE*). Logs are written to the audit_logs table via AuditService. A formal logging-inventory document covering Spring access logs, application logs and audit logs is still pending. | H3: AuditAction.java; AuditService.java; application.properties#logging
A4: V16.2 | B4: General Logging
A5: V16.2 | B5: General Logging | C5: V16.2.1 | D5: Verify that each log entry includes necessary metadata (such as when, where, who, what) that would allow for a detailed investigation of the timeline when an event happens. | E5: 2 | F5: Compliant | G5: Highly applicable to Kryptos. Log entries should include enough metadata to support investigation, namely when, who, what, and where the event occurred.
A6: V16.2 | B6: General Logging | C6: V16.2.2 | D6: Verify that time sources for all logging components are synchronized, and that timestamps in security event metadata use UTC or include an explicit time zone offset. UTC is recommended to ensure consistency across distributed systems and to prevent confusion during daylight saving time transitions. | E6: 2 | F6: Compliant | G6: Highly applicable to Kryptos. Logging timestamps should be consistent across components and should use UTC or an explicit time zone offset to support reliable audit and investigation.
A7: V16.2 | B7: General Logging | C7: V16.2.3 | D7: Verify that the application only stores or broadcasts logs to the files and services that are documented in the log inventory. | E7: 2 | F7: Not Applicable
A8: V16.2 | B8: General Logging | C8: V16.2.4 | D8: Verify that logs can be read and correlated by the log processor that is in use, preferably by using a common logging format. | E8: 2 | F8: Not Applicable
A9: V16.2 | B9: General Logging | C9: V16.2.5 | D9: Verify that when logging sensitive data, the application enforces logging based on the data's protection level. For example, it may not be allowed to log certain data, such as credentials or payment details. Other data, such as session tokens, may only be logged by being hashed or masked, either in full or partially. | E9: 2 | F9: Not Applicable
A10: V16.3 | B10: Security Events
A11: V16.3 | B11: Security Events | C11: V16.3.1 | D11: Verify that all authentication operations are logged, including successful and unsuccessful attempts. Additional metadata, such as the type of authentication or factors used, should also be collected. | E11: 2 | F11: Compliant | G11: Highly applicable to Kryptos. Both successful and unsuccessful authentication attempts should be logged together with relevant metadata for audit and investigation.
A12: V16.3 | B12: Security Events | C12: V16.3.2 | D12: Verify that failed authorization attempts are logged. For L3, this must include logging all authorization decisions, including logging when sensitive data is accessed (without logging the sensitive data itself). | E12: 2 | F12: Compliant | G12: Highly applicable to Kryptos. Failed authorization attempts and relevant access decisions over sensitive resources should be logged without exposing sensitive data in the logs.
A13: V16.3 | B13: Security Events | C13: V16.3.3 | D13: Verify that the application logs the security events that are defined in the documentation and also logs attempts to bypass the security controls, such as input validation, business logic, and anti-automation. | E13: 2 | F13: Compliant | G13: Highly applicable to Kryptos. Security events and attempts to bypass security controls should be defined and included in the application logging strategy.
A14: V16.3 | B14: Security Events | C14: V16.3.4 | D14: Verify that the application logs unexpected errors and security control failures such as backend TLS failures. | E14: 2 | F14: Compliant | G14: Highly applicable to Kryptos. Unexpected errors and security control failures should be logged to support monitoring, investigation, and incident response.
A15: V16.4 | B15: Log Protection
A16: V16.4 | B16: Log Protection | C16: V16.4.1 | D16: Verify that all logging components appropriately encode data to prevent log injection. | E16: 2 | F16: Not Applicable
A17: V16.4 | B17: Log Protection | C17: V16.4.2 | D17: Verify that logs are protected from unauthorized access and cannot be modified. | E17: 2 | F17: Compliant | G17: Audit logs are read-only over the API (AuditController has only GET endpoints, gated by hasAnyRole(ADMIN, AUDITOR)). AuditLog @PreUpdate / @PreRemove throw UnsupportedOperationException, blocking modification at the JPA layer. SHA-256 hash chain detects tampering. | H17: AuditController.java; AuditLog.java; AuditLogTest; AuditServiceTest.log_shouldBuildHashChain
A18: V16.4 | B18: Log Protection | C18: V16.4.3 | D18: Verify that logs are securely transmitted to a logically separate system for analysis, detection, alerting, and escalation. The aim is to ensure that if the application is breached, the logs are not compromised. | E18: 2 | F18: Compliant | G18: Highly applicable to Kryptos. Security-relevant logs should ideally be transmitted or preserved in a logically separate system or storage location to reduce the risk of compromise.
A19: V16.5 | B19: Error Handling
A20: V16.5 | B20: Error Handling | C20: V16.5.1 | D20: Verify that a generic message is returned to the consumer when an unexpected or security-sensitive error occurs, ensuring no exposure of sensitive internal system data such as stack traces, queries, secret keys, and tokens. | E20: 2 | F20: Compliant | G20: GlobalExceptionHandler.handleGeneric returns {"error":"Internal server error"} with HTTP 500 for any uncategorized Exception, never propagating stack traces, SQL fragments or internal paths. EncryptionException and ResourceNotFoundException return generic messages. | H20: backend/src/main/java/com/kryptos/shared/exception/GlobalExceptionHandler.java
A21: V16.5 | B21: Error Handling | C21: V16.5.2 | D21: Verify that the application continues to operate securely when external resource access fails, for example, by using patterns such as circuit breakers or graceful degradation. | E21: 2 | F21: Not Applicable
A22: V16.5 | B22: Error Handling | C22: V16.5.3 | D22: Verify that the application fails gracefully and securely, including when an exception occurs, preventing fail-open conditions such as processing a transaction despite errors resulting from validation logic. | E22: 2 | F22: Not Applicable
A23: V16.5 | B23: Error Handling | C23: V16.5.4 | D23: Verify that a "last resort" error handler is defined which will catch all unhandled exceptions. This is both to avoid losing error details that must go to log files and to ensure that an error does not take down the entire application process, leading to a loss of availability. | E23: 3 | F23: Not Applicable

Sheet V17 - WebRTC
A1: Section ID | B1: Section Name | C1: Req ID | D1: Description | E1: Level | F1: Status | G1: Observations | H1: Reference / Link
A2: V17.1 | B2: TURN Server
A3: V17.1 | B3: TURN Server | C3: V17.1.1 | D3: Verify that the Traversal Using Relays around NAT (TURN) service only allows access to IP addresses that are not reserved for special purposes (e.g., internal networks, broadcast, loopback). Note that this applies to both IPv4 and IPv6 addresses. | E3: 2 | F3: Not Applicable
A4: V17.1 | B4: TURN Server | C4: V17.1.2 | D4: Verify that the Traversal Using Relays around NAT (TURN) service is not susceptible to resource exhaustion when legitimate users attempt to open a large number of ports on the TURN server. | E4: 3 | F4: Not Applicable
A5: V17.2 | B5: Media
A6: V17.2 | B6: Media | C6: V17.2.1 | D6: Verify that the key for the Datagram Transport Layer Security (DTLS) certificate is managed and protected based on the documented policy for management of cryptographic keys. | E6: 2 | F6: Not Applicable
A7: V17.2 | B7: Media | C7: V17.2.2 | D7: Verify that the media server is configured to use and support approved Datagram Transport Layer Security (DTLS) cipher suites and a secure protection profile for the DTLS Extension for establishing keys for the Secure Real-time Transport Protocol (DTLS-SRTP). | E7: 2 | F7: Not Applicable
A8: V17.2 | B8: Media | C8: V17.2.3 | D8: Verify that Secure Real-time Transport Protocol (SRTP) authentication is checked at the media server to prevent Real-time Transport Protocol (RTP) injection attacks from leading to either a Denial of Service condition or audio or video media insertion into media streams. | E8: 2 | F8: Not Applicable
A9: V17.2 | B9: Media | C9: V17.2.4 | D9: Verify that the media server is able to continue processing incoming media traffic when encountering malformed Secure Real-time Transport Protocol (SRTP) packets. | E9: 2 | F9: Not Applicable
A10: V17.2 | B10: Media | C10: V17.2.5 | D10: Verify that the media server is able to continue processing incoming media traffic during a flood of Secure Real-time Transport Protocol (SRTP) packets from legitimate users. | E10: 3 | F10: Not Applicable
A11: V17.2 | B11: Media | C11: V17.2.6 | D11: Verify that the media server is not susceptible to the "ClientHello" Race Condition vulnerability in Datagram Transport Layer Security (DTLS) by checking if the media server is publicly known to be vulnerable or by performing the race condition test. | E11: 3 | F11: Not Applicable
A12: V17.2 | B12: Media | C12: V17.2.7 | D12: Verify that any audio or video recording mechanisms associated with the media server are able to continue processing incoming media traffic during a flood of Secure Real-time Transport Protocol (SRTP) packets from legitimate users. | E12: 3 | F12: Not Applicable
A13: V17.2 | B13: Media | C13: V17.2.8 | D13: Verify that the Datagram Transport Layer Security (DTLS) certificate is checked against the Session Description Protocol (SDP) fingerprint attribute, terminating the media stream if the check fails, to ensure the authenticity of the media stream. | E13: 3 | F13: Not Applicable
A14: V17.3 | B14: Signaling
A15: V17.3 | B15: Signaling | C15: V17.3.1 | D15: Verify that the signaling server is able to continue processing legitimate incoming signaling messages during a flood attack. This should be achieved by implementing rate limiting at the signaling level. | E15: 2 | F15: Not Applicable
A16: V17.3 | B16: Signaling | C16: V17.3.2 | D16: Verify that the signaling server is able to continue processing legitimate signaling messages when encountering malformed signaling message that could cause a denial of service condition. This could include implementing input validation, safely handling integer overflows, preventing buffer overflows, and employing other robust error-handling techniques. | E16: 2 | F16: Not Applicable
